[{"revid": 1351957040, "parentid": 1351898205, "user": "HalfOfAnOrange", "timestamp": "2026-05-01T04:18:44Z", "size": 244499, "sha1": "3feba90cc5f4ac60182bcf9f75bb1cfd36b39545", "comment": "/* Domestic sponsors */", "tags": ["wikieditor"], "is_revert": false, "reverted_editor": null}, {"revid": 1351957077, "parentid": 1351957040, "user": "HalfOfAnOrange", "timestamp": "2026-05-01T04:19:14Z", "size": 244503, "sha1": "fb9717bbe13a61476756ffb3aa5e07ec74a563ba", "comment": "/* Domestic sponsors */", "tags": ["wikieditor"], "is_revert": false, "reverted_editor": null}, {"revid": 1351957613, "parentid": 1351957077, "user": "HalfOfAnOrange", "timestamp": "2026-05-01T04:25:00Z", "size": 244819, "sha1": "d0b98fd1e558b8c527691532f6d89a08ddee1b3b", "comment": "/* Domestic sponsors */", "tags": ["wikieditor"], "is_revert": false, "reverted_editor": null}, {"revid": 1351959195, "parentid": 1351957613, "user": "HalfOfAnOrange", "timestamp": "2026-05-01T04:41:44Z", "size": 244908, "sha1": "3f46b5df86c91cebc19535a22b82084834f65573", "comment": "/* Domestic sponsors */", "tags": ["wikieditor"], "is_revert": false, "reverted_editor": null}, {"revid": 1351959474, "parentid": 1351959195, "user": "HalfOfAnOrange", "timestamp": "2026-05-01T04:43:53Z", "size": 244935, "sha1": "3913c7a36a0ab497a67786baacea18298b6f3ead", "comment": "/* Domestic sponsors */", "tags": ["wikieditor"], "is_revert": false, "reverted_editor": null}, {"revid": 1352110013, "parentid": 1351959474, "user": "S.A. Julio", "timestamp": "2026-05-02T02:58:19Z", "size": 244913, "sha1": "ff608a2188292e2b1ee29ffccc910f3fa97808b0", "comment": "add reflist for report group", "tags": ["AWB"], "is_revert": false, "reverted_editor": null}, {"revid": 1352129865, "parentid": 1352110013, "user": "Yaavarr", "timestamp": "2026-05-02T06:32:39Z", "size": 246560, "sha1": "9fd15de9297f8e94d99ca274b3f41bb42886a43e", "comment": "/* Iran's participation */", "tags": ["wikieditor"], "is_revert": false, "reverted_editor": null}, {"revid": 1352138559, "parentid": 1352129865, "user": "Assadzadeh", "timestamp": "2026-05-02T08:34:21Z", "size": 246614, "sha1": "577ca6d820443169d8b4f4c984fe7cc7ec5580aa", "comment": "Added missing author to source and added access date.", "tags": ["mobile edit", "mobile web edit", "visualeditor", "advanced mobile edit"], "is_revert": false, "reverted_editor": null}, {"revid": 1352244402, "parentid": 1352138559, "user": "Kodak11111", "timestamp": "2026-05-03T01:26:36Z", "size": 246610, "sha1": "0e93f7e84cdf74e6990b248116dadd5c639a46a5", "comment": "/* Iran's participation */ The concerns section needs to be cleaned up somehow, it's so long and hard to follow", "tags": ["mobile edit", "mobile web edit", "advanced mobile edit"], "is_revert": false, "reverted_editor": null}, {"revid": 1352297063, "parentid": 1352244402, "user": "FootyFactsUK", "timestamp": "2026-05-03T10:59:49Z", "size": 247037, "sha1": "f72b5898089967c9d5105b218a9dce452fa56605", "comment": "/* Prize money */ The Preparation money has been increased by FIFA in 76th Congress.", "tags": ["visualeditor-switched", "wikieditor"], "is_revert": false, "reverted_editor": null}, {"revid": 1352310394, "parentid": 1352297063, "user": "Assadzadeh", "timestamp": "2026-05-03T13:06:58Z", "size": 246604, "sha1": "eac6ca151c1551c090107d3418a36b8e205e0b28", "comment": "Removed outdated sources, added missing author to current source, and cleanup.", "tags": ["mobile edit", "mobile web edit", "visualeditor", "advanced mobile edit"], "is_revert": false, "reverted_editor": null}, {"revid": 1352310772, "parentid": 1352310394, "user": "Assadzadeh", "timestamp": "2026-05-03T13:09:54Z", "size": 246609, "sha1": "b98b5ab8a0f51ac425b1a05106feb10cc17d84e0", "comment": "/* Prize money */", "tags": ["mobile edit", "mobile web edit", "advanced mobile edit"], "is_revert": false, "reverted_editor": null}, {"revid": 1352311810, "parentid": 1352310772, "user": "Assadzadeh", "timestamp": "2026-05-03T13:19:27Z", "size": 246616, "sha1": "96a2cc45eebced52dc38ddf3b0f870bd19a689a1", "comment": "Further fine tuning", "tags": ["mobile edit", "mobile web edit", "visualeditor", "advanced mobile edit"], "is_revert": false, "reverted_editor": null}, {"revid": 1352373079, "parentid": 1352311810, "user": "HalfOfAnOrange", "timestamp": "2026-05-03T20:50:38Z", "size": 246596, "sha1": "3f57355c6583c0a09da234cde5e15c90d0fbce37", "comment": "/* Domestic sponsors */", "tags": ["wikieditor"], "is_revert": false, "reverted_editor": null}, {"revid": 1352373837, "parentid": 1352373079, "user": "HalfOfAnOrange", "timestamp": "2026-05-03T20:56:31Z", "size": 246832, "sha1": "e050afbbcbcb8078b58ef211a315c31911a060e3", "comment": "/* Domestic sponsors */", "tags": ["wikieditor"], "is_revert": false, "reverted_editor": null}, {"revid": 1352393509, "parentid": 1352373837, "user": "Assadzadeh", "timestamp": "2026-05-03T23:19:39Z", "size": 246863, "sha1": "d4b797e3c7969e4f500723cf4541ab1da361c9c3", "comment": "", "tags": ["mobile edit", "mobile web edit", "visualeditor", "advanced mobile edit"], "is_revert": false, "reverted_editor": null}, {"revid": 1352447176, "parentid": 1352393509, "user": "Yaavarr", "timestamp": "2026-05-04T06:41:49Z", "size": 249163, "sha1": "9c7a9eee9c7d52ca285defcd7b58436044d0f4e0", "comment": "FIFA Peace Prize", "tags": ["mw-reverted", "wikieditor"], "is_revert": false, "reverted_editor": null}, {"revid": 1352450621, "parentid": 1352447176, "user": "49ersBelongInSanFrancisco", "timestamp": "2026-05-04T07:33:30Z", "size": 246863, "sha1": "d4b797e3c7969e4f500723cf4541ab1da361c9c3", "comment": "Reverted 1 edit by [[Special:Contributions/Yaavarr|Yaavarr]] ([[User talk:Yaavarr|talk]]) to last revision by Assadzadeh", "tags": ["mw-undo", "twinkle"], "is_revert": true, "reverted_editor": "Yaavarr"}, {"revid": 1352573078, "parentid": 1352450621, "user": "FootyFactsUK", "timestamp": "2026-05-05T00:53:45Z", "size": 246862, "sha1": "9c6b6fb272a34362e302a8aa90487caf726b3a13", "comment": "/* Prize money */", "tags": ["wikieditor"], "is_revert": false, "reverted_editor": null}, {"revid": 1352672885, "parentid": 1352573078, "user": "HalfOfAnOrange", "timestamp": "2026-05-05T16:06:06Z", "size": 246845, "sha1": "0cf91bef1c58410ccf1306f1e3c41f535a6c1517", "comment": "/* Team base camps */", "tags": ["wikieditor"], "is_revert": false, "reverted_editor": null}, {"revid": 1352673038, "parentid": 1352672885, "user": "HalfOfAnOrange", "timestamp": "2026-05-05T16:07:11Z", "size": 246841, "sha1": "9a6753b2325f8edc2236df59e0ad378405b173c2", "comment": "/* Team base camps */", "tags": ["wikieditor"], "is_revert": false, "reverted_editor": null}, {"revid": 1352673619, "parentid": 1352673038, "user": "HalfOfAnOrange", "timestamp": "2026-05-05T16:11:01Z", "size": 246901, "sha1": "eee2613007156a489b08284bee6e6095a2ee1d73", "comment": "/* Team base camps */", "tags": ["wikieditor"], "is_revert": false, "reverted_editor": null}, {"revid": 1352714926, "parentid": 1352673619, "user": "Schwede66", "timestamp": "2026-05-05T20:57:57Z", "size": 246915, "sha1": "338db179c81ff1a2a9f8689de6901829571e302d", "comment": "/* Host selection */ {{cn}}", "tags": ["wikieditor"], "is_revert": false, "reverted_editor": null}, {"revid": 1352715094, "parentid": 1352714926, "user": "Schwede66", "timestamp": "2026-05-05T20:59:08Z", "size": 246921, "sha1": "b02988d3e76c151dae9f4369b09a3e02214e5394", "comment": "/* Format and expansion */ {{cn}}", "tags": ["wikieditor"], "is_revert": false, "reverted_editor": null}, {"revid": 1352715356, "parentid": 1352715094, "user": "Schwede66", "timestamp": "2026-05-05T21:00:55Z", "size": 246927, "sha1": "841a74fbf150eacc6e9442f799a7c232f4bce2f0", "comment": "/* Venues */ {{cn}}", "tags": ["wikieditor"], "is_revert": false, "reverted_editor": null}, {"revid": 1352716335, "parentid": 1352715356, "user": "HalfOfAnOrange", "timestamp": "2026-05-05T21:09:35Z", "size": 246911, "sha1": "94a74a621e507490e369705c9973935972676c21", "comment": "/* Team base camps */", "tags": ["wikieditor"], "is_revert": false, "reverted_editor": null}, {"revid": 1352718655, "parentid": 1352716335, "user": "AnomieBOT", "timestamp": "2026-05-05T21:29:44Z", "size": 246967, "sha1": "2badef21bd1f4c9f05f9281151375c7d09a86fa1", "comment": "Dating maintenance tags: {{Cn}}", "tags": [], "is_revert": false, "reverted_editor": null}, {"revid": 1352819804, "parentid": 1352718655, "user": "Billsmith60", "timestamp": "2026-05-06T12:29:20Z", "size": 246965, "sha1": "59394bb59b6747d1d61edbde84af128171c3d1f8", "comment": "spacing", "tags": [], "is_revert": false, "reverted_editor": null}, {"revid": 1352967568, "parentid": 1352819804, "user": "MacFleet76", "timestamp": "2026-05-07T09:45:20Z", "size": 247389, "sha1": "8b632b5edcbb3889443c016aa9bf25344c763bf1", "comment": "Fifa defence of ticket pricing", "tags": ["visualeditor", "editcheck-newreference"], "is_revert": false, "reverted_editor": null}, {"revid": 1352974472, "parentid": 1352967568, "user": "Kodak11111", "timestamp": "2026-05-07T11:14:43Z", "size": 247385, "sha1": "56bf09e9539d03d422342fdd9f629d29a7f7ba8b", "comment": "/* Ticket prices */", "tags": ["mobile edit", "mobile web edit", "advanced mobile edit"], "is_revert": false, "reverted_editor": null}, {"revid": 1352976483, "parentid": 1352974472, "user": "1995hoo", "timestamp": "2026-05-07T11:38:15Z", "size": 247397, "sha1": "b1d2383914bc887947a2320f9d1baa3032e5a543", "comment": "/* Ticket prices */ \"they\" is ambiguous (and misleading when the apparent antecedent is singular).", "tags": ["wikieditor"], "is_revert": false, "reverted_editor": null}, {"revid": 1353026352, "parentid": 1352976483, "user": "S.A. Julio", "timestamp": "2026-05-07T18:33:05Z", "size": 248272, "sha1": "5a6a1e9dd4930e3d001a35aa0f9ffcadef9d95ab", "comment": "/* Teams */ add squads section", "tags": ["wikieditor"], "is_revert": false, "reverted_editor": null}, {"revid": 1353091430, "parentid": 1353026352, "user": "S.A. Julio", "timestamp": "2026-05-08T03:23:47Z", "size": 248329, "sha1": "742c12f3106c0f0526ea003f22c25168ffc3da53", "comment": "/* Discipline */ table caption", "tags": ["wikieditor"], "is_revert": false, "reverted_editor": null}, {"revid": 1353091646, "parentid": 1353091430, "user": "S.A. Julio", "timestamp": "2026-05-08T03:25:29Z", "size": 248334, "sha1": "f7f391417b7d7d8517298d370a9f6a140d5309aa", "comment": "/* top */ move to note as is the common style in many articles", "tags": ["wikieditor"], "is_revert": false, "reverted_editor": null}, {"revid": 1353091846, "parentid": 1353091646, "user": "S.A. Julio", "timestamp": "2026-05-08T03:27:16Z", "size": 248337, "sha1": "f601dac14321ea3137a8bb6f04212159d97a2819", "comment": "/* top */ upper-alpha", "tags": ["wikieditor"], "is_revert": false, "reverted_editor": null}, {"revid": 1353093555, "parentid": 1353091846, "user": "S.A. Julio", "timestamp": "2026-05-08T03:47:29Z", "size": 248289, "sha1": "bca8f6cf2c335e6ec509e7fafe11c8347a9fe5f7", "comment": "/* Venues */ no need to pipe, we should be using the", "tags": ["wikieditor"], "is_revert": false, "reverted_editor": null}, {"revid": 1353093628, "parentid": 1353093555, "user": "S.A. Julio", "timestamp": "2026-05-08T03:48:30Z", "size": 248296, "sha1": "a9f9b5a2edad7ffe4dd94363dc376d224b26c772", "comment": "dummy edit to add to last edit summary: we should be using the [[WP:COMMONNAME]] of the stadium reflected in the article title, so piping is unnecessary", "tags": ["wikieditor"], "is_revert": false, "reverted_editor": null}, {"revid": 1353169083, "parentid": 1353093628, "user": "VonXionixx87", "timestamp": "2026-05-08T16:01:38Z", "size": 248854, "sha1": "1d94dece6787ccf77b3082a4714c058edb168dc9", "comment": "/* Music */", "tags": ["wikieditor"], "is_revert": false, "reverted_editor": null}, {"revid": 1353169210, "parentid": 1353169083, "user": "VonXionixx87", "timestamp": "2026-05-08T16:02:24Z", "size": 248854, "sha1": "2a87bd7603a111d9b9529cd2a5e410fd7e0d8652", "comment": "/* Music */", "tags": ["wikieditor"], "is_revert": false, "reverted_editor": null}, {"revid": 1353170163, "parentid": 1353169210, "user": "HalfOfAnOrange", "timestamp": "2026-05-08T16:09:09Z", "size": 248853, "sha1": "80b69feee355f3e1d646c0de2d0981502ec3b2bb", "comment": "/* Music */", "tags": ["wikieditor"], "is_revert": false, "reverted_editor": null}, {"revid": 1353175659, "parentid": 1353170163, "user": "HalfOfAnOrange", "timestamp": "2026-05-08T16:57:00Z", "size": 250541, "sha1": "a5b433a5dcf057f7e91eaa8a4c21cf6539b0d143", "comment": "/* Officiating */", "tags": ["disambiguator-link-added", "wikieditor"], "is_revert": false, "reverted_editor": null}, {"revid": 1353175817, "parentid": 1353175659, "user": "HalfOfAnOrange", "timestamp": "2026-05-08T16:58:11Z", "size": 250542, "sha1": "607a99da5cc315f812cc3bb5c34d79e77798b60d", "comment": "/* Opening ceremony */", "tags": ["wikieditor"], "is_revert": false, "reverted_editor": null}, {"revid": 1353177368, "parentid": 1353175817, "user": "Kodak11111", "timestamp": "2026-05-08T17:10:25Z", "size": 250565, "sha1": "0478de967acfe302763c631f72842ff49b080b65", "comment": "/* Opening ceremony */", "tags": ["mobile edit", "mobile web edit", "advanced mobile edit"], "is_revert": false, "reverted_editor": null}, {"revid": 1353179753, "parentid": 1353177368, "user": "1995hoo", "timestamp": "2026-05-08T17:30:48Z", "size": 250546, "sha1": "22efa645d002233b7327345f71eba33d7134b1a9", "comment": "/* Opening ceremony */ [[MOS:DATECOMMA]] and elimination of redundancy.", "tags": ["wikieditor"], "is_revert": false, "reverted_editor": null}, {"revid": 1353192265, "parentid": 1353179753, "user": "S.A. Julio", "timestamp": "2026-05-08T19:09:28Z", "size": 250084, "sha1": "7bafbd5cfafd4357e554c28381be1288e7cc62e3", "comment": "/* Discipline */ update", "tags": ["wikieditor"], "is_revert": false, "reverted_editor": null}, {"revid": 1353237012, "parentid": 1353192265, "user": "Sportsfan 1234", "timestamp": "2026-05-09T01:33:02Z", "size": 250086, "sha1": "37b7dcf92168fa638816700705e9a5ebec68c6fa", "comment": "/* Opening ceremony */", "tags": ["wikieditor"], "is_revert": false, "reverted_editor": null}, {"revid": 1353306694, "parentid": 1353237012, "user": "HalfOfAnOrange", "timestamp": "2026-05-09T13:47:34Z", "size": 250886, "sha1": "ef3e51d00aa3d90563ad3dd3680eda4ef9cb6db5", "comment": "/* Opening ceremonies */", "tags": ["wikieditor"], "is_revert": false, "reverted_editor": null}, {"revid": 1353307410, "parentid": 1353306694, "user": "HalfOfAnOrange", "timestamp": "2026-05-09T13:52:48Z", "size": 250882, "sha1": "36bbfcf53ad87832cfd95b152edfb28615c083b2", "comment": "/* Opening ceremonies */", "tags": ["wikieditor"], "is_revert": false, "reverted_editor": null}, {"revid": 1353318445, "parentid": 1353307410, "user": "HalfOfAnOrange", "timestamp": "2026-05-09T15:23:44Z", "size": 250887, "sha1": "57cfc5a50035a5b2c32d6f5110aeb9b307dda049", "comment": "/* Opening ceremonies */", "tags": ["wikieditor"], "is_revert": false, "reverted_editor": null}, {"revid": 1353536247, "parentid": 1353318445, "user": "JJMC89 bot III", "timestamp": "2026-05-10T21:03:04Z", "size": 250841, "sha1": "bdc15a0d30349d5ef7511dec9d01179427782d69", "comment": "Removing [[:Category:Canada\u2013Mexico sports relations]] per [[Wikipedia:Categories for discussion/Log/2026 March 21#Category:Bilateral cricket relations of Canada]]", "tags": [], "is_revert": false, "reverted_editor": null}, {"revid": 1353537505, "parentid": 1353536247, "user": "JJMC89 bot III", "timestamp": "2026-05-10T21:10:14Z", "size": 250788, "sha1": "d26d905ceedd5ae6726a6b62a8dc5fd37e7b4866", "comment": "Removing [[:Category:Canada\u2013United States sports relations]] per [[Wikipedia:Categories for discussion/Log/2026 March 21#Category:Bilateral cricket relations of Canada]]", "tags": [], "is_revert": false, "reverted_editor": null}, {"revid": 1353550536, "parentid": 1353537505, "user": "HalfOfAnOrange", "timestamp": "2026-05-10T22:54:39Z", "size": 251346, "sha1": "ef6c6866c3071f85fea48a8b03425996ea1c8ab4", "comment": "/* Iran war */", "tags": ["wikieditor"], "is_revert": false, "reverted_editor": null}, {"revid": 1353551720, "parentid": 1353550536, "user": "Quuxplusone", "timestamp": "2026-05-10T23:05:09Z", "size": 251394, "sha1": "42854d834874891e17c69ffa7615fee185ae29e3", "comment": "/* FIFA Peace Prize */ past tense for singular events", "tags": ["wikieditor"], "is_revert": false, "reverted_editor": null}, {"revid": 1353566623, "parentid": 1353551720, "user": "HalfOfAnOrange", "timestamp": "2026-05-11T01:25:39Z", "size": 251528, "sha1": "81acbe8fe4be551c5178fbcc78c9d76cd5de44fb", "comment": "/* Iran war */", "tags": ["wikieditor"], "is_revert": false, "reverted_editor": null}, {"revid": 1353576122, "parentid": 1353566623, "user": "Lf8u2", "timestamp": "2026-05-11T02:29:03Z", "size": 250925, "sha1": "00e7c60df46bb09261498741591a5229b1b032f7", "comment": "/* Protests and massacres in Iran */ Source misrepresented in that [[Sardar Pashaei]] called for a ban from IOC competitions, not the FIFA World Cup.", "tags": ["wikieditor"], "is_revert": false, "reverted_editor": null}, {"revid": 1353578946, "parentid": 1353576122, "user": "Assadzadeh", "timestamp": "2026-05-11T02:51:06Z", "size": 250931, "sha1": "5be3c4c9941a17e7f2f8c8f519292422a8a8c998", "comment": "", "tags": ["mobile edit", "mobile web edit", "visualeditor", "advanced mobile edit"], "is_revert": false, "reverted_editor": null}, {"revid": 1353584820, "parentid": 1353578946, "user": "Publicwalrus", "timestamp": "2026-05-11T03:44:29Z", "size": 251294, "sha1": "a04b6a9dd788b63a94f763f9d05dd0ce771cf513", "comment": "/* Team base camps */ Added Morocco source. Needs citations for cape verde and iraq", "tags": ["wikieditor"], "is_revert": false, "reverted_editor": null}, {"revid": 1353584940, "parentid": 1353584820, "user": "Publicwalrus", "timestamp": "2026-05-11T03:45:32Z", "size": 251315, "sha1": "ae12053cf830da6d2c608437afca478d7e43b9c9", "comment": "/* Team base camps */", "tags": ["wikieditor"], "is_revert": false, "reverted_editor": null}, {"revid": 1353587170, "parentid": 1353584940, "user": "AnomieBOT", "timestamp": "2026-05-11T04:06:36Z", "size": 251343, "sha1": "4ce135462cc83026777fc6c7a0bc5407c4a587eb", "comment": "Dating maintenance tags: {{Citation needed}}", "tags": [], "is_revert": false, "reverted_editor": null}, {"revid": 1353597488, "parentid": 1353587170, "user": "Publicwalrus", "timestamp": "2026-05-11T05:51:12Z", "size": 251354, "sha1": "66619bbc18de588afd8aa5b61fe06fb0da6826fa", "comment": "/* Team base camps */", "tags": ["wikieditor"], "is_revert": false, "reverted_editor": null}, {"revid": 1353635734, "parentid": 1353597488, "user": "PinkFalafel", "timestamp": "2026-05-11T13:18:07Z", "size": 251733, "sha1": "6c523c6a4c4fe91db6e7699dc5951e556cfc5b11", "comment": "/* Iran war */ New news :)", "tags": ["visualeditor", "editcheck-newreference", "editcheck-newcontent"], "is_revert": false, "reverted_editor": null}, {"revid": 1353637610, "parentid": 1353635734, "user": "FePe55", "timestamp": "2026-05-11T13:33:29Z", "size": 251735, "sha1": "ff5a574e02f608c21f4c82fc0a534140de3b9a07", "comment": "typo", "tags": ["wikieditor"], "is_revert": false, "reverted_editor": null}, {"revid": 1353644584, "parentid": 1353637610, "user": "Assadzadeh", "timestamp": "2026-05-11T14:25:10Z", "size": 250858, "sha1": "310cfaa626932b369885ce113d582b9cc5d8dd5c", "comment": "Moving to the end of the section \u2013 part 1", "tags": ["mobile edit", "mobile web edit", "advanced mobile edit"], "is_revert": false, "reverted_editor": null}, {"revid": 1353645119, "parentid": 1353644584, "user": "Assadzadeh", "timestamp": "2026-05-11T14:29:40Z", "size": 251731, "sha1": "5ff7bc6df053955f3e4fa5171e1a33874a61fa53", "comment": "Moving to the end of the section \u2013 part 2", "tags": ["mobile edit", "mobile web edit", "visualeditor", "advanced mobile edit"], "is_revert": false, "reverted_editor": null}, {"revid": 1353659382, "parentid": 1353645119, "user": "Assadzadeh", "timestamp": "2026-05-11T16:19:36Z", "size": 251352, "sha1": "68663a7e21a810a03efea1a40ae15fff3724052c", "comment": "[[WP:CRYSTALBALL]]", "tags": ["mobile edit", "mobile web edit", "visualeditor", "advanced mobile edit"], "is_revert": false, "reverted_editor": null}, {"revid": 1353717493, "parentid": 1353659382, "user": "Desmond Hobson", "timestamp": "2026-05-11T23:32:18Z", "size": 251537, "sha1": "ff3fae9477e017bdbfb794ee85eb2583ae04bca4", "comment": "/* Team base camps */ Explanation of different names for some training venues", "tags": ["wikieditor"], "is_revert": false, "reverted_editor": null}, {"revid": 1353718524, "parentid": 1353717493, "user": "Kodak11111", "timestamp": "2026-05-11T23:41:23Z", "size": 251502, "sha1": "7944849a5087de815b4b0891362752c072a4de96", "comment": "", "tags": ["mobile edit", "mobile web edit", "advanced mobile edit"], "is_revert": false, "reverted_editor": null}, {"revid": 1353744488, "parentid": 1353718524, "user": "HalfOfAnOrange", "timestamp": "2026-05-12T02:38:05Z", "size": 248776, "sha1": "d9aca2eb5c57f31cd24d1277785a5865cbdb5c73", "comment": "/* Team base camps */", "tags": ["mw-reverted", "wikieditor"], "is_revert": false, "reverted_editor": null}, {"revid": 1353799249, "parentid": 1353744488, "user": "MediaKyle", "timestamp": "2026-05-12T12:36:42Z", "size": 248693, "sha1": "d732466e4f99e921a5a923d6f9d1b8ac142e3862", "comment": "Remove Facebook as reference", "tags": ["mw-reverted", "wikieditor"], "is_revert": false, "reverted_editor": null}, {"revid": 1353815324, "parentid": 1353799249, "user": "Assadzadeh", "timestamp": "2026-05-12T14:51:47Z", "size": 248633, "sha1": "948e0295e5f3e8077483a82eea7d8f1b19df1c3b", "comment": "X is not a reliable source", "tags": ["mobile edit", "mobile web edit", "visualeditor", "advanced mobile edit", "mw-reverted"], "is_revert": false, "reverted_editor": null}, {"revid": 1353837332, "parentid": 1353815324, "user": "Publicwalrus", "timestamp": "2026-05-12T17:44:29Z", "size": 251502, "sha1": "7944849a5087de815b4b0891362752c072a4de96", "comment": "", "tags": ["mw-manual-revert", "wikieditor"], "is_revert": true, "reverted_editor": "Assadzadeh"}, {"revid": 1353837749, "parentid": 1353837332, "user": "Publicwalrus", "timestamp": "2026-05-12T17:47:54Z", "size": 251454, "sha1": "ed967cc19519afaf5ace937b34b6cc86d05c5ecd", "comment": "/* Team base camps */ Removed Iraq and Cape Verde camps until source is provided", "tags": ["wikieditor"], "is_revert": false, "reverted_editor": null}, {"revid": 1353839803, "parentid": 1353837749, "user": "HalfOfAnOrange", "timestamp": "2026-05-12T18:02:48Z", "size": 251600, "sha1": "d96ee23ffa320408f6d2742b2edccffd59734397", "comment": "Undid revision [[Special:Diff/1353837749|1353837749]] by [[Special:Contributions/Publicwalrus|Publicwalrus]] ([[User talk:Publicwalrus|talk]])", "tags": ["wikieditor"], "is_revert": true, "reverted_editor": "Publicwalrus"}, {"revid": 1353843619, "parentid": 1353839803, "user": "Manutguy", "timestamp": "2026-05-12T18:33:40Z", "size": 251661, "sha1": "b8b1aeadf3f8acfd4c46aff17204ff54aae59064", "comment": "/* Qualification */", "tags": ["wikieditor"], "is_revert": false, "reverted_editor": null}, {"revid": 1353844004, "parentid": 1353843619, "user": "1995hoo", "timestamp": "2026-05-12T18:37:02Z", "size": 251657, "sha1": "e3acb1afdf9fa034d51bc2c8d65b83e5f2415a13", "comment": "/* Qualification */ grammar (incorrect uses of the plural form, as further evidenced by the disconnect that edit created in \"was the only former champions\").", "tags": ["wikieditor"], "is_revert": false, "reverted_editor": null}, {"revid": 1353844056, "parentid": 1353844004, "user": "1995hoo", "timestamp": "2026-05-12T18:37:30Z", "size": 251656, "sha1": "15d09c4aae04e7f4ba55980a8943f1afb30da2e4", "comment": "/* Qualification */ oops, missed one.", "tags": ["wikieditor"], "is_revert": false, "reverted_editor": null}, {"revid": 1353844131, "parentid": 1353844056, "user": "1995hoo", "timestamp": "2026-05-12T18:38:07Z", "size": 251655, "sha1": "745801e0990b0a259e1cdcffc0f82eb4a50930c4", "comment": "/* Qualification */ and one more.", "tags": ["wikieditor"], "is_revert": false, "reverted_editor": null}, {"revid": 1353878603, "parentid": 1353844131, "user": "Meganinja202", "timestamp": "2026-05-12T23:07:42Z", "size": 252539, "sha1": "c51c92936acc0440aada675bfa930961a8cda7c6", "comment": "/* Broadcasting rights */", "tags": ["visualeditor", "editcheck-newreference", "editcheck-newcontent"], "is_revert": false, "reverted_editor": null}, {"revid": 1353883228, "parentid": 1353878603, "user": "Kodak11111", "timestamp": "2026-05-12T23:59:14Z", "size": 252393, "sha1": "6ce266b02ceb51401ecc0272b46c3761eb800462", "comment": "/* Broadcasting rights */", "tags": ["mobile edit", "mobile web edit", "advanced mobile edit"], "is_revert": false, "reverted_editor": null}, {"revid": 1353908889, "parentid": 1353883228, "user": "Assadzadeh", "timestamp": "2026-05-13T03:17:36Z", "size": 252578, "sha1": "d5c22cf4e5b20bd67b5b10abd7e1cfc2840efa05", "comment": "Fixed reference", "tags": ["mobile edit", "mobile web edit", "visualeditor", "advanced mobile edit"], "is_revert": false, "reverted_editor": null}, {"revid": 1353911864, "parentid": 1353908889, "user": "Assadzadeh", "timestamp": "2026-05-13T03:39:46Z", "size": 252565, "sha1": "cbb6e2c1c0283c34cb1a2f4e1eccd0b9df61a37e", "comment": "Tournament has not occurred yet, so it doesn't need to be in the past tense. Also, national teams are singular in American English.", "tags": ["mobile edit", "mobile web edit", "visualeditor", "advanced mobile edit"], "is_revert": false, "reverted_editor": null}, {"revid": 1354071843, "parentid": 1353911864, "user": "S.A. Julio", "timestamp": "2026-05-14T03:37:44Z", "size": 252727, "sha1": "81355568fe7444697bf2b03aaadbfe8b7f52b536", "comment": "/* Venues */ use sort value instead of calling a template due to post-expand include size issues", "tags": ["wikieditor"], "is_revert": false, "reverted_editor": null}, {"revid": 1354083513, "parentid": 1354071843, "user": "HalfOfAnOrange", "timestamp": "2026-05-14T05:22:38Z", "size": 252777, "sha1": "25ae0d65700e06da7c0e8664b0f8d2edb80d8e4c", "comment": "/* Domestic sponsors */", "tags": ["wikieditor"], "is_revert": false, "reverted_editor": null}, {"revid": 1354095452, "parentid": 1354083513, "user": "S.A. Julio", "timestamp": "2026-05-14T08:01:25Z", "size": 252862, "sha1": "a2ef92b1716a01344b964a6166deb9b2600ee164", "comment": "remove templates per [[WP:BIDIRECTIONAL]]; and [[Template:2026 FIFA World Cup third-place table]] has a large impact on the post-expand include size, so linking to its section on the knockout sub-article instead", "tags": ["wikieditor"], "is_revert": false, "reverted_editor": null}, {"revid": 1354111888, "parentid": 1354095452, "user": "King10", "timestamp": "2026-05-14T11:19:28Z", "size": 253383, "sha1": "2f148451ff32a9d73d2fce308ae41acb78c1aa8b", "comment": "/* Final match halftime show */ adding info", "tags": ["wikieditor"], "is_revert": false, "reverted_editor": null}, {"revid": 1354113190, "parentid": 1354111888, "user": "1995hoo", "timestamp": "2026-05-14T11:34:08Z", "size": 253384, "sha1": "baaa97beb508fdec513335472e0e11d2731df409", "comment": "/* Final match halftime show */ missing comma.", "tags": ["wikieditor"], "is_revert": false, "reverted_editor": null}, {"revid": 1354120516, "parentid": 1354113190, "user": "HalfOfAnOrange", "timestamp": "2026-05-14T12:46:17Z", "size": 253624, "sha1": "19336b77ee6469fa587f0b1bdd11668471abe5f5", "comment": "/* Domestic sponsors */", "tags": ["wikieditor"], "is_revert": false, "reverted_editor": null}, {"revid": 1354137108, "parentid": 1354120516, "user": "HalfOfAnOrange", "timestamp": "2026-05-14T15:05:04Z", "size": 253964, "sha1": "1c57005e1cd59ecabddf135b13c2f366d3a8c411", "comment": "/* Sponsorships */", "tags": ["wikieditor"], "is_revert": false, "reverted_editor": null}, {"revid": 1354160357, "parentid": 1354137108, "user": "Chris1834", "timestamp": "2026-05-14T17:59:12Z", "size": 253982, "sha1": "2feae9fe1cf53907e5baa5d5fc5c9abe9e50ba86", "comment": "/* Concerns */ Added link to list article", "tags": ["visualeditor-wikitext"], "is_revert": false, "reverted_editor": null}, {"revid": 1354161295, "parentid": 1354160357, "user": "Chris1834", "timestamp": "2026-05-14T18:06:13Z", "size": 236798, "sha1": "b363cf8915c45c6798016bac7184f77eafc656b0", "comment": "/* Controversies */ Eliminating items that aren't as prevalent and can be on the list article only", "tags": ["visualeditor-wikitext"], "is_revert": false, "reverted_editor": null}, {"revid": 1354162698, "parentid": 1354161295, "user": "Chris1834", "timestamp": "2026-05-14T18:17:05Z", "size": 221406, "sha1": "2551159b49325eaf0b72d994c3ff0146fb70cadf", "comment": "/* Iran's participation */", "tags": ["visualeditor-wikitext"], "is_revert": false, "reverted_editor": null}, {"revid": 1354163228, "parentid": 1354162698, "user": "Chris1834", "timestamp": "2026-05-14T18:21:15Z", "size": 219103, "sha1": "55393e6b583c0d6dd15a21548b5c422cfdd82a68", "comment": "/* Controversies */", "tags": ["visualeditor-wikitext"], "is_revert": false, "reverted_editor": null}, {"revid": 1354171873, "parentid": 1354163228, "user": "S.A. Julio", "timestamp": "2026-05-14T19:29:57Z", "size": 219039, "sha1": "febf9c1b508a6f095a65de9ec135f7d41a9d82b2", "comment": "/* Draw */ the draw result is better suited for the [[2026 FIFA World Cup seeding]] sub-article; for this page, readers can see below which teams ended up in which groups", "tags": ["wikieditor"], "is_revert": false, "reverted_editor": null}, {"revid": 1354172158, "parentid": 1354171873, "user": "S.A. Julio", "timestamp": "2026-05-14T19:31:45Z", "size": 219000, "sha1": "f56fd761fbccf7ebfa3705081053077c93b834cb", "comment": "/* Controversies */ adjust section headings", "tags": ["wikieditor"], "is_revert": false, "reverted_editor": null}, {"revid": 1354224317, "parentid": 1354172158, "user": "S.A. Julio", "timestamp": "2026-05-15T02:13:59Z", "size": 220213, "sha1": "599402f0f6c47e9936a86e91a55fdcb439b126f2", "comment": "add prose to format in group/knockout stage sections", "tags": ["wikieditor"], "is_revert": false, "reverted_editor": null}, {"revid": 1354226466, "parentid": 1354224317, "user": "S.A. Julio", "timestamp": "2026-05-15T02:28:42Z", "size": 220072, "sha1": "06f03b40157061a17c2b55ee5222c100fdc9c982", "comment": "/* Music */ remove redlinks, unclear if independently notable", "tags": ["wikieditor"], "is_revert": false, "reverted_editor": null}, {"revid": 1354228362, "parentid": 1354226466, "user": "S.A. Julio", "timestamp": "2026-05-15T02:41:09Z", "size": 219741, "sha1": "dfd5020a6d0a13f0d29cf5922e221741efaadb75", "comment": "/* Posters */ the list of artists for each host city isn't particularly notable; use more encyclopedic voice", "tags": ["wikieditor"], "is_revert": false, "reverted_editor": null}, {"revid": 1354228442, "parentid": 1354228362, "user": "S.A. Julio", "timestamp": "2026-05-15T02:41:45Z", "size": 219725, "sha1": "e7b8ed4f4f70b2394b2cfbfaf61cb510e0e2b8ba", "comment": "/* Branding */ doesn't require a subsection", "tags": ["wikieditor"], "is_revert": false, "reverted_editor": null}, {"revid": 1354239522, "parentid": 1354228442, "user": "Kodak11111", "timestamp": "2026-05-15T04:26:24Z", "size": 219724, "sha1": "31e62ba72b3776ad5cac9efb2e982363091c4241", "comment": "", "tags": ["mobile edit", "mobile web edit", "advanced mobile edit"], "is_revert": false, "reverted_editor": null}, {"revid": 1354264313, "parentid": 1354239522, "user": "S.A. Julio", "timestamp": "2026-05-15T09:39:26Z", "size": 215326, "sha1": "bf6f5985fa6e7eaaf76e6e3343270345cb9cdad1", "comment": "moved ticket price criticism to controversies article", "tags": ["wikieditor"], "is_revert": false, "reverted_editor": null}, {"revid": 1354265506, "parentid": 1354264313, "user": "S.A. Julio", "timestamp": "2026-05-15T09:56:56Z", "size": 215377, "sha1": "ffab794801a4713dff23e0452dd1d45b8a77afda", "comment": "/* Statistics */ see also", "tags": ["wikieditor"], "is_revert": false, "reverted_editor": null}, {"revid": 1354270124, "parentid": 1354265506, "user": "S.A. Julio", "timestamp": "2026-05-15T10:46:42Z", "size": 215409, "sha1": "7bf543a879f0191c491d0d3cff78819a1244c2e2", "comment": "/* Mascots */ main article", "tags": ["wikieditor"], "is_revert": false, "reverted_editor": null}, {"revid": 1354275697, "parentid": 1354270124, "user": "Cyfraw", "timestamp": "2026-05-15T11:42:42Z", "size": 215421, "sha1": "afe4acf9b07edd6e4b46a86acadd046ff57a33cd", "comment": "/* Qualification */", "tags": ["visualeditor-wikitext"], "is_revert": false, "reverted_editor": null}, {"revid": 1354297531, "parentid": 1354275697, "user": "HalfOfAnOrange", "timestamp": "2026-05-15T14:46:37Z", "size": 215874, "sha1": "c24b85980d11e63cc784b8df72653ce826945338", "comment": "/* Music */", "tags": ["wikieditor"], "is_revert": false, "reverted_editor": null}, {"revid": 1354297933, "parentid": 1354297531, "user": "Kodak11111", "timestamp": "2026-05-15T14:50:01Z", "size": 215875, "sha1": "fe65a4d7b34cb2cd84006e5b62cf5ccf72e17de1", "comment": "", "tags": ["mobile edit", "mobile web edit", "advanced mobile edit"], "is_revert": false, "reverted_editor": null}, {"revid": 1354415360, "parentid": 1354297933, "user": "Mohammed Shahidullah-Bin-Anwar", "timestamp": "2026-05-16T07:56:43Z", "size": 216871, "sha1": "a3bfb4eb5b4ea8e3472202ddfe549ae99d9d0a19", "comment": "/* Iran's participation */", "tags": ["wikieditor"], "is_revert": false, "reverted_editor": null}, {"revid": 1354415506, "parentid": 1354415360, "user": "Nandanmwikipedia", "timestamp": "2026-05-16T07:58:40Z", "size": 216883, "sha1": "63544bdc45ead247f4bc39226c64743541bb7084", "comment": "/* */ Added an internal website courtesy and reference Linklint to the 3 nations from Wikipedia.", "tags": ["mobile edit", "mobile web edit", "mw-reverted"], "is_revert": false, "reverted_editor": null}, {"revid": 1354415896, "parentid": 1354415506, "user": "Saleah253", "timestamp": "2026-05-16T08:03:10Z", "size": 216931, "sha1": "474848a309c4763c00f1fe535d9e2aa08c2077cd", "comment": "/* Teams */", "tags": ["mobile edit", "mobile web edit", "mw-reverted"], "is_revert": false, "reverted_editor": null}, {"revid": 1354443626, "parentid": 1354415896, "user": "Kodak11111", "timestamp": "2026-05-16T13:19:41Z", "size": 216919, "sha1": "7e354236a2f53e34c957f68e532f2a457c5da3de", "comment": "Undid revision [[Special:Diff/1354415506|1354415506]] by [[Special:Contributions/Nandanmwikipedia|Nandanmwikipedia]] ([[User talk:Nandanmwikipedia|talk]]) over linking", "tags": ["mw-undo", "mobile edit", "mobile web edit", "advanced mobile edit", "wikieditor"], "is_revert": true, "reverted_editor": "Saleah253"}, {"revid": 1354443989, "parentid": 1354443626, "user": "Kodak11111", "timestamp": "2026-05-16T13:22:46Z", "size": 216899, "sha1": "8a1c29b8c17105ab5601acf5f828d094b3099be4", "comment": "/* Iran's participation */ I feel this section is still too long and should be mostly moved to the new controversies page", "tags": ["mobile edit", "mobile web edit", "advanced mobile edit"], "is_revert": false, "reverted_editor": null}, {"revid": 1354450463, "parentid": 1354443989, "user": "S.A. Julio", "timestamp": "2026-05-16T14:19:02Z", "size": 216851, "sha1": "04c772b7830c1ccfc893284e7244182c33193649", "comment": "Undid revision [[Special:Diff/1354415896|1354415896]] by [[Special:Contributions/Saleah253|Saleah253]] ([[User talk:Saleah253|talk]]) the squads section is already immediately above this...", "tags": ["mw-undo", "wikieditor"], "is_revert": true, "reverted_editor": "Kodak11111"}, {"revid": 1354618891, "parentid": 1354450463, "user": "Emperorpenguinn", "timestamp": "2026-05-17T12:16:57Z", "size": 217644, "sha1": "6c1fbb184ec76b5ee318e2ada804986154bc653c", "comment": "/* Immigration */ Added a note about the U.S. waiving the visa bond requirement for fans from five African countries, as well as the travel ban on fans from Iran and Haiti, under the Immigration controversies section.", "tags": ["visualeditor-wikitext"], "is_revert": false, "reverted_editor": null}, {"revid": 1354643590, "parentid": 1354618891, "user": "Amakuru", "timestamp": "2026-05-17T15:26:49Z", "size": 208005, "sha1": "e92cb6c895ae4b1b791d3a12f6845e6b995871ce", "comment": "/* Awards */ removing section on \"FIFA Peace Prize\"; this isn't really related to the 2026 world cup and this page is already quite long, before the tournament has even begun", "tags": ["mw-reverted", "wikieditor"], "is_revert": false, "reverted_editor": null}, {"revid": 1354648720, "parentid": 1354643590, "user": "Jkudlick", "timestamp": "2026-05-17T16:04:17Z", "size": 217644, "sha1": "6c1fbb184ec76b5ee318e2ada804986154bc653c", "comment": "Undid revision [[Special:Diff/1354643590|1354643590]] by [[Special:Contributions/Amakuru|Amakuru]] ([[User talk:Amakuru|talk]]) undoing removal of a relatively controversial section; this removal should have come only after discussion", "tags": ["mw-undo", "mw-reverted", "wikieditor"], "is_revert": true, "reverted_editor": "Amakuru"}, {"revid": 1354651697, "parentid": 1354648720, "user": "Amakuru", "timestamp": "2026-05-17T16:23:27Z", "size": 208005, "sha1": "e92cb6c895ae4b1b791d3a12f6845e6b995871ce", "comment": "Undid revision [[Special:Diff/1354648720|1354648720]] by [[Special:Contributions/Jkudlick|Jkudlick]] ([[User talk:Jkudlick|talk]]) - please see my talk page comment, and [[WP:ONUS]]. If you want to include this material on this page, you need to demonstrate that there is a consensus for it. If (and only if) such a consensus develops in the talk page discussion then you can re-add", "tags": ["mw-undo", "mw-reverted", "wikieditor"], "is_revert": true, "reverted_editor": "Jkudlick"}, {"revid": 1354656852, "parentid": 1354651697, "user": "Amakuru", "timestamp": "2026-05-17T16:57:22Z", "size": 217644, "sha1": "6c1fbb184ec76b5ee318e2ada804986154bc653c", "comment": "Undid revision [[Special:Diff/1354651697|1354651697]] by [[Special:Contributions/Amakuru|Amakuru]] ([[User talk:Amakuru|talk]]) - self-reverting for now; it seems we may retain a small amount of material on this topic, so original version should be the starting point for that.....", "tags": ["mw-undo", "wikieditor"], "is_revert": true, "reverted_editor": "Amakuru"}, {"revid": 1354666517, "parentid": 1354656852, "user": "Kodak11111", "timestamp": "2026-05-17T17:57:00Z", "size": 217625, "sha1": "922119cc902354f9c7e870dc9ec52e246854bc50", "comment": "/* Immigration */", "tags": ["mobile edit", "mobile web edit", "advanced mobile edit"], "is_revert": false, "reverted_editor": null}, {"revid": 1354697692, "parentid": 1354666517, "user": "Emmanuelope", "timestamp": "2026-05-17T21:16:01Z", "size": 217656, "sha1": "c006004b3ea304a8758d39d1dea7b819ab6e77b7", "comment": "/* Match ball */ This one is a more professional picture", "tags": ["wikieditor"], "is_revert": false, "reverted_editor": null}, {"revid": 1354715835, "parentid": 1354697692, "user": "Jkudlick", "timestamp": "2026-05-17T23:00:26Z", "size": 215460, "sha1": "04a713b61a2153ff42be1581ba2ec0768cea3419", "comment": "/* Group stage */ reducing [[WP:PEIS]] by 207 KiB; see [[Talk:2026 FIFA World Cup#Issues with the post-expand include size]]", "tags": ["mw-reverted", "wikieditor"], "is_revert": false, "reverted_editor": null}, {"revid": 1354800090, "parentid": 1354715835, "user": "MuhammadKamran12", "timestamp": "2026-05-18T08:37:56Z", "size": 215464, "sha1": "c4766c05d75a09084dfc2db1e1d535e3ce43671c", "comment": "Added Internal Link", "tags": ["visualeditor"], "is_revert": false, "reverted_editor": null}, {"revid": 1354827587, "parentid": 1354800090, "user": "Nxhon25", "timestamp": "2026-05-18T13:15:02Z", "size": 215475, "sha1": "17ddb3c22513979207a7d3d51cbef1ff603242af", "comment": "", "tags": ["mobile edit", "mobile app edit", "ios app edit", "app-section-source"], "is_revert": false, "reverted_editor": null}, {"revid": 1354829134, "parentid": 1354827587, "user": "HalfOfAnOrange", "timestamp": "2026-05-18T13:26:46Z", "size": 215867, "sha1": "7e9fccfc432525a4f05dc1e3d9f627d4ecbe8269", "comment": "/* Regional supporters */", "tags": ["wikieditor"], "is_revert": false, "reverted_editor": null}, {"revid": 1354830326, "parentid": 1354829134, "user": "Chris1834", "timestamp": "2026-05-18T13:35:07Z", "size": 215863, "sha1": "87734f0c9c10f676eb35c493a63ac0c1c69c4766", "comment": "", "tags": ["visualeditor-wikitext"], "is_revert": false, "reverted_editor": null}, {"revid": 1354831767, "parentid": 1354830326, "user": "Chris1834", "timestamp": "2026-05-18T13:45:13Z", "size": 196836, "sha1": "914d4bdbb79aa0020ebca5418e6f2980d4c7a05f", "comment": "/* Controversies */ Moved all info to secondary article as everything being added was just put on this page.", "tags": ["visualeditor-wikitext", "mw-reverted"], "is_revert": false, "reverted_editor": null}, {"revid": 1354847233, "parentid": 1354831767, "user": "HalfOfAnOrange", "timestamp": "2026-05-18T15:35:36Z", "size": 196840, "sha1": "444781d95b35bbd1a76205dc8d668750c364193c", "comment": "/* Domestic sponsors */", "tags": ["wikieditor"], "is_revert": false, "reverted_editor": null}, {"revid": 1354847384, "parentid": 1354847233, "user": "HalfOfAnOrange", "timestamp": "2026-05-18T15:36:38Z", "size": 196840, "sha1": "580db6b4e9161bc54fd91e398d35265b291fa1e3", "comment": "/* Domestic sponsors */", "tags": ["wikieditor"], "is_revert": false, "reverted_editor": null}, {"revid": 1354850386, "parentid": 1354847384, "user": "Amakuru", "timestamp": "2026-05-18T15:58:54Z", "size": 189083, "sha1": "a17483975942593d972b5c53278136f2632e15e0", "comment": "a cut down version of the FIFA Peace Prize detail has been copied over to [[2026 FIFA World Cup draw]], per the talk page; as such, I'm reducing the coverage of that here to one sentence among the summary of the draw; no further coverage of it is warranted on this page", "tags": ["wikieditor"], "is_revert": false, "reverted_editor": null}, {"revid": 1354852283, "parentid": 1354850386, "user": "1995hoo", "timestamp": "2026-05-18T16:12:15Z", "size": 189082, "sha1": "1bf395e57a0048bbf1e7a7ee166ec36cb947e933", "comment": "/* Draw */ typo (British spelling in article tagged for American English).", "tags": ["wikieditor"], "is_revert": false, "reverted_editor": null}, {"revid": 1354895930, "parentid": 1354852283, "user": "S.A. Julio", "timestamp": "2026-05-18T20:46:27Z", "size": 208109, "sha1": "34cea13a79dc4df866edb42a38ac4f3f986f9981", "comment": "Undid revision [[Special:Diff/1354831767|1354831767]] by [[Special:Contributions/Chris1834|Chris1834]] ([[User talk:Chris1834|talk]]) while this section can be shortened, [[Wikipedia:Summary style|summary style]] needs to be used. There should be more detail than one sentence, and some references are required", "tags": ["mw-undo", "wikieditor"], "is_revert": true, "reverted_editor": "1995hoo"}, {"revid": 1354896317, "parentid": 1354895930, "user": "S.A. Julio", "timestamp": "2026-05-18T20:49:09Z", "size": 210305, "sha1": "8193e3b51fd3f11602253dbcce735615c74a68b8", "comment": "Undid revision [[Special:Diff/1354715835|1354715835]] by [[Special:Contributions/Jkudlick|Jkudlick]] ([[User talk:Jkudlick|talk]]) this could be an option, but a number of editors on the talk page were in favor of other options first, and only this as a last resort. Better there be a clear consensus before making such a change", "tags": ["mw-undo", "wikieditor"], "is_revert": true, "reverted_editor": "S.A. Julio"}, {"revid": 1355009536, "parentid": 1354896317, "user": "Cyfraw", "timestamp": "2026-05-19T12:25:07Z", "size": 210123, "sha1": "e145b6c3d197f760538c6702902dd43572552854", "comment": "/* Immigration */ Already repeated no need", "tags": ["visualeditor-wikitext"], "is_revert": false, "reverted_editor": null}, {"revid": 1355027364, "parentid": 1355009536, "user": "O cara l\u00e1 do fusca", "timestamp": "2026-05-19T14:43:40Z", "size": 210138, "sha1": "16e60c12c98bc6a282bb3a5e836fda01c3c51587", "comment": "/* Broadcasting rights */", "tags": ["visualeditor"], "is_revert": false, "reverted_editor": null}, {"revid": 1355036915, "parentid": 1355027364, "user": "SD1942561", "timestamp": "2026-05-19T15:51:36Z", "size": 210238, "sha1": "484724a014b3d8981e3b17d33ff560db60f694c9", "comment": "/* Qualification */ Mentioned that this will be the first World Cup since 2010 to not feature Costa Rica", "tags": ["wikieditor"], "is_revert": false, "reverted_editor": null}, {"revid": 1355037669, "parentid": 1355036915, "user": "1995hoo", "timestamp": "2026-05-19T15:56:51Z", "size": 210237, "sha1": "159d1baec587bc4bb532511cf120732380189134", "comment": "/* Qualification */ ENGVAR.", "tags": ["wikieditor"], "is_revert": false, "reverted_editor": null}, {"revid": 1355066919, "parentid": 1355037669, "user": "Ronnnaldo7", "timestamp": "2026-05-19T19:19:44Z", "size": 213501, "sha1": "be0b2db85ffe8dddeb7eea115be5dfcd67add308", "comment": "Restore important context", "tags": ["wikieditor"], "is_revert": false, "reverted_editor": null}, {"revid": 1355067276, "parentid": 1355066919, "user": "Ronnnaldo7", "timestamp": "2026-05-19T19:22:19Z", "size": 213501, "sha1": "1354dc2bb7aec8dbf561c7c9ebf7bd5e927cacd1", "comment": "Order", "tags": ["wikieditor"], "is_revert": false, "reverted_editor": null}, {"revid": 1355087857, "parentid": 1355067276, "user": "Meganinja202", "timestamp": "2026-05-19T21:48:22Z", "size": 214083, "sha1": "4b4c5f4d822d20f89f91440986da3d5024885454", "comment": "/* Merchandise */ - video game", "tags": ["visualeditor", "editcheck-newreference", "editcheck-newcontent"], "is_revert": false, "reverted_editor": null}, {"revid": 1355091692, "parentid": 1355087857, "user": "Meganinja202", "timestamp": "2026-05-19T22:12:44Z", "size": 214603, "sha1": "e6f7ab20672fd6bc28f0c89e891f0cdbc29a626b", "comment": "/* Merchandise */", "tags": ["visualeditor", "editcheck-newreference"], "is_revert": false, "reverted_editor": null}, {"revid": 1355097276, "parentid": 1355091692, "user": "Ronnnaldo7", "timestamp": "2026-05-19T22:49:07Z", "size": 215316, "sha1": "277f8818e05e3fafdbad6c0dd3e8e55256160635", "comment": "Update", "tags": ["wikieditor"], "is_revert": false, "reverted_editor": null}, {"revid": 1355097422, "parentid": 1355097276, "user": "Ronnnaldo7", "timestamp": "2026-05-19T22:50:04Z", "size": 215320, "sha1": "d4e922f958dd98e263ab7d8c41aefeb8098065ca", "comment": "[[WP:Link]]", "tags": ["wikieditor"], "is_revert": false, "reverted_editor": null}, {"revid": 1355097829, "parentid": 1355097422, "user": "Meganinja202", "timestamp": "2026-05-19T22:53:04Z", "size": 216185, "sha1": "c60f8b0adb1fca07c682130292500130be42ac9c", "comment": "updates on iran and halftime final", "tags": ["visualeditor", "editcheck-newreference", "editcheck-newcontent"], "is_revert": false, "reverted_editor": null}, {"revid": 1355098040, "parentid": 1355097829, "user": "Meganinja202", "timestamp": "2026-05-19T22:54:50Z", "size": 216162, "sha1": "1a7bb3f29679df81453fc06bfde01a3e4233392e", "comment": "", "tags": ["visualeditor"], "is_revert": false, "reverted_editor": null}, {"revid": 1355132877, "parentid": 1355098040, "user": "S.A. Julio", "timestamp": "2026-05-20T02:48:30Z", "size": 216227, "sha1": "af38d8a7a0a683adae60520993be5821452e39d9", "comment": "/* */ add code for future use", "tags": ["wikieditor"], "is_revert": false, "reverted_editor": null}, {"revid": 1355146798, "parentid": 1355132877, "user": "Kodak11111", "timestamp": "2026-05-20T04:49:21Z", "size": 216772, "sha1": "a5b7e559138a99242cd4aabdbf2b8c28409c8053", "comment": "", "tags": ["mobile edit", "mobile web edit", "visualeditor", "advanced mobile edit", "editcheck-newreference"], "is_revert": false, "reverted_editor": null}, {"revid": 1355147156, "parentid": 1355146798, "user": "Kodak11111", "timestamp": "2026-05-20T04:52:52Z", "size": 216775, "sha1": "51c518436dcd7a6f8a6adc4d27eadb60eb4eeeb1", "comment": "", "tags": ["mobile edit", "mobile web edit", "visualeditor", "advanced mobile edit"], "is_revert": false, "reverted_editor": null}, {"revid": 1355147724, "parentid": 1355147156, "user": "Kodak11111", "timestamp": "2026-05-20T04:58:36Z", "size": 216852, "sha1": "29609fa432fd3413c5581d14244e40df517e8f7d", "comment": "", "tags": ["mobile edit", "mobile web edit", "visualeditor", "advanced mobile edit", "editcheck-newreference"], "is_revert": false, "reverted_editor": null}, {"revid": 1355149098, "parentid": 1355147724, "user": "Kodak11111", "timestamp": "2026-05-20T05:11:00Z", "size": 216852, "sha1": "ddef4db7a6e623a4d8ce4718a17b3507f06fc514", "comment": "", "tags": ["mobile edit", "mobile web edit", "visualeditor", "advanced mobile edit"], "is_revert": false, "reverted_editor": null}, {"revid": 1355151058, "parentid": 1355149098, "user": "Kodak11111", "timestamp": "2026-05-20T05:18:12Z", "size": 216848, "sha1": "fdb95fefa31d2a6b712f3f0c6109903d3608b44e", "comment": "/* External links */", "tags": ["mobile edit", "mobile web edit", "advanced mobile edit"], "is_revert": false, "reverted_editor": null}, {"revid": 1355151581, "parentid": 1355151058, "user": "Kodak11111", "timestamp": "2026-05-20T05:23:15Z", "size": 217111, "sha1": "5611ee316748bec1c55faf8b9aa570223ec90978", "comment": "", "tags": ["mobile edit", "mobile web edit", "visualeditor", "advanced mobile edit", "editcheck-newreference"], "is_revert": false, "reverted_editor": null}, {"revid": 1355152514, "parentid": 1355151581, "user": "Kodak11111", "timestamp": "2026-05-20T05:33:30Z", "size": 217653, "sha1": "577b7ac975d50b923e76847193459e8dbb316fd9", "comment": "", "tags": ["mobile edit", "mobile web edit", "visualeditor", "advanced mobile edit", "editcheck-newreference"], "is_revert": false, "reverted_editor": null}, {"revid": 1355153042, "parentid": 1355152514, "user": "Kodak11111", "timestamp": "2026-05-20T05:39:16Z", "size": 217966, "sha1": "f91d512b45c436fae7b217bacc3340e16bcf8532", "comment": "", "tags": ["mobile edit", "mobile web edit", "visualeditor", "advanced mobile edit", "editcheck-newreference"], "is_revert": false, "reverted_editor": null}, {"revid": 1355153991, "parentid": 1355153042, "user": "Kodak11111", "timestamp": "2026-05-20T05:49:15Z", "size": 218197, "sha1": "321b95239d36725b6304c57dcbb18b572d0bf9a7", "comment": "", "tags": ["mobile edit", "mobile web edit", "visualeditor", "advanced mobile edit", "editcheck-newreference"], "is_revert": false, "reverted_editor": null}, {"revid": 1355154544, "parentid": 1355153991, "user": "Kodak11111", "timestamp": "2026-05-20T05:53:50Z", "size": 218729, "sha1": "2622dfe7f98092faecb82f668a1c079a4d3e5e5c", "comment": "", "tags": ["mobile edit", "mobile web edit", "visualeditor", "advanced mobile edit", "editcheck-newreference"], "is_revert": false, "reverted_editor": null}, {"revid": 1355155288, "parentid": 1355154544, "user": "Kodak11111", "timestamp": "2026-05-20T05:59:17Z", "size": 218977, "sha1": "9686a2ad4a23eada5461d072f16a3c6e94131b1e", "comment": "", "tags": ["mobile edit", "mobile web edit", "visualeditor", "advanced mobile edit", "editcheck-newreference"], "is_revert": false, "reverted_editor": null}, {"revid": 1355183389, "parentid": 1355155288, "user": "Sangeth30", "timestamp": "2026-05-20T10:36:59Z", "size": 219047, "sha1": "518c314b2f30a3dda8edc50758aa2ce87d667667", "comment": "", "tags": ["visualeditor"], "is_revert": false, "reverted_editor": null}, {"revid": 1355197279, "parentid": 1355183389, "user": "90svintagecassettecd", "timestamp": "2026-05-20T12:52:33Z", "size": 219037, "sha1": "748f1085dbf17d8f37785f272df67b9edf6ac36c", "comment": "", "tags": ["mobile edit", "mobile web edit", "advanced mobile edit"], "is_revert": false, "reverted_editor": null}, {"revid": 1355199182, "parentid": 1355197279, "user": "HalfOfAnOrange", "timestamp": "2026-05-20T13:10:48Z", "size": 219108, "sha1": "3d5fb8a9a24be20412615302af47930119b67c6d", "comment": "/* Domestic sponsors */", "tags": ["wikieditor"], "is_revert": false, "reverted_editor": null}, {"revid": 1355199397, "parentid": 1355199182, "user": "HalfOfAnOrange", "timestamp": "2026-05-20T13:12:34Z", "size": 219149, "sha1": "472f4ad57e6f2d87e020b27d6b64d1805befa43d", "comment": "/* Domestic sponsors */", "tags": ["wikieditor"], "is_revert": false, "reverted_editor": null}, {"revid": 1355199704, "parentid": 1355199397, "user": "HalfOfAnOrange", "timestamp": "2026-05-20T13:15:35Z", "size": 219297, "sha1": "e01fd0286be87a42dc8c8cc6f08e6d3aacf4a93a", "comment": "/* Domestic sponsors */", "tags": ["wikieditor"], "is_revert": false, "reverted_editor": null}, {"revid": 1355206347, "parentid": 1355199704, "user": "Kodak11111", "timestamp": "2026-05-20T14:17:25Z", "size": 219236, "sha1": "b4ee01ca10839ed1857bda4b4d6aba6f381970de", "comment": "", "tags": ["mobile edit", "mobile web edit", "visualeditor", "advanced mobile edit"], "is_revert": false, "reverted_editor": null}, {"revid": 1355207108, "parentid": 1355206347, "user": "1995hoo", "timestamp": "2026-05-20T14:24:14Z", "size": 219222, "sha1": "a6e7956f8c46a2b102bd5f6d04028cc3b7a3cbbd", "comment": "/* Final match halftime show */ The first sentence of this section arguably violated [[WP:NPOV]]. \"Akin to what happened in\" comes across as saying something bad happened or something went wrong. Certainly some people object to the halftime show, but the second paragraph addresses that issue.", "tags": ["wikieditor"], "is_revert": false, "reverted_editor": null}, {"revid": 1355216871, "parentid": 1355207108, "user": "Spiffy sperry", "timestamp": "2026-05-20T15:49:29Z", "size": 219218, "sha1": "48453ac22c6292ed8676cd2e8f592b1e6578cc76", "comment": "/* Iran's participation */ remove extra word", "tags": ["wikieditor"], "is_revert": false, "reverted_editor": null}, {"revid": 1355234466, "parentid": 1355216871, "user": "HalfOfAnOrange", "timestamp": "2026-05-20T18:05:44Z", "size": 219696, "sha1": "10976118745ffccaadde155a4720217595c844f1", "comment": "/* Climate */", "tags": ["wikieditor"], "is_revert": false, "reverted_editor": null}, {"revid": 1355234571, "parentid": 1355234466, "user": "HalfOfAnOrange", "timestamp": "2026-05-20T18:06:32Z", "size": 220200, "sha1": "68f8ad51d066ba8b27f79f649423bef85814596b", "comment": "/* Music */", "tags": ["disambiguator-link-added", "wikieditor"], "is_revert": false, "reverted_editor": null}, {"revid": 1355236654, "parentid": 1355234571, "user": "1995hoo", "timestamp": "2026-05-20T18:23:14Z", "size": 220205, "sha1": "48b9e027ccbf31bb913b159a6287fcdb14382658", "comment": "/* Music */ grammar and failure to use commas properly.", "tags": ["wikieditor"], "is_revert": false, "reverted_editor": null}, {"revid": 1355236803, "parentid": 1355236654, "user": "1995hoo", "timestamp": "2026-05-20T18:24:34Z", "size": 220221, "sha1": "fb42fa4be3ab2db382b4d059faee8ec451d2b5de", "comment": "/* Music */ further grammar corrections. A song is an inanimate thing. It does not release itself.", "tags": ["wikieditor"], "is_revert": false, "reverted_editor": null}, {"revid": 1355237516, "parentid": 1355236803, "user": "HalfOfAnOrange", "timestamp": "2026-05-20T18:29:47Z", "size": 220237, "sha1": "14b43748fe0d142963bde6ae5ec96fa3afc87ccd", "comment": "/* Music */", "tags": ["wikieditor"], "is_revert": false, "reverted_editor": null}, {"revid": 1355239641, "parentid": 1355237516, "user": "HalfOfAnOrange", "timestamp": "2026-05-20T18:47:18Z", "size": 220247, "sha1": "8581cbe6638550be65296cd71cc92a344b36ebaa", "comment": "/* Climate */", "tags": ["wikieditor"], "is_revert": false, "reverted_editor": null}, {"revid": 1355328329, "parentid": 1355239641, "user": "ExcarnateSojourner", "timestamp": "2026-05-21T06:18:07Z", "size": 220246, "sha1": "df40b9a498bb8ae1244e3f3a9de6ffcb834b6a1d", "comment": "/* Draw */ typo", "tags": ["visualeditor-wikitext"], "is_revert": false, "reverted_editor": null}, {"revid": 1355378240, "parentid": 1355328329, "user": "Axios512", "timestamp": "2026-05-21T14:05:07Z", "size": 220498, "sha1": "5e128063d6cd643354253ee016c940043c503694", "comment": "+ref", "tags": ["wikieditor"], "is_revert": false, "reverted_editor": null}, {"revid": 1355385452, "parentid": 1355378240, "user": "JalenBarks", "timestamp": "2026-05-21T15:01:34Z", "size": 220489, "sha1": "bd5bf695e670535221e4d4db26f09f0f85544b59", "comment": "clean up", "tags": ["AWB"], "is_revert": false, "reverted_editor": null}, {"revid": 1355387088, "parentid": 1355385452, "user": "Kodak11111", "timestamp": "2026-05-21T15:12:59Z", "size": 220515, "sha1": "490bc4ab380057cdfdc564ba8c4a53df5a029b0b", "comment": "/* Qualification */", "tags": ["mobile edit", "mobile web edit", "visualeditor", "advanced mobile edit"], "is_revert": false, "reverted_editor": null}, {"revid": 1355458582, "parentid": 1355387088, "user": "HalfOfAnOrange", "timestamp": "2026-05-22T00:07:21Z", "size": 220602, "sha1": "4dcfb7f8936d5c9959c76ae65789bca553186772", "comment": "/* Domestic sponsors */", "tags": ["disambiguator-link-added", "wikieditor"], "is_revert": false, "reverted_editor": null}, {"revid": 1355458638, "parentid": 1355458582, "user": "HalfOfAnOrange", "timestamp": "2026-05-22T00:07:49Z", "size": 220619, "sha1": "2b8ef87169f6efef7b87e107a2ba64aae2f31df7", "comment": "/* Domestic sponsors */", "tags": ["wikieditor"], "is_revert": false, "reverted_editor": null}, {"revid": 1355491348, "parentid": 1355458638, "user": "Meganinja202", "timestamp": "2026-05-22T04:39:06Z", "size": 220741, "sha1": "ee0997314fd2aa65ccaf6877bc67ecb37179d348", "comment": "/* Other products */ - some review", "tags": ["visualeditor"], "is_revert": false, "reverted_editor": null}, {"revid": 1355512557, "parentid": 1355491348, "user": "AxelSj\u00f6gren", "timestamp": "2026-05-22T07:58:27Z", "size": 220740, "sha1": "0ed0c619a2de21e5f8c49fb4c1863982319790dc", "comment": "/* Other products */", "tags": ["mobile edit", "mobile web edit"], "is_revert": false, "reverted_editor": null}, {"revid": 1355690957, "parentid": 1355512557, "user": "R.tuor", "timestamp": "2026-05-23T09:28:15Z", "size": 221356, "sha1": "8b08a1c91e284c3fdcd5c10d9375e4f0cafc6795", "comment": "summarizing the bldy", "tags": ["mw-reverted", "wikieditor"], "is_revert": false, "reverted_editor": null}, {"revid": 1355691274, "parentid": 1355690957, "user": "R.tuor", "timestamp": "2026-05-23T09:33:09Z", "size": 221405, "sha1": "83d4031ae0e28cc02c856b58c324e9e189b998fd", "comment": "", "tags": ["mw-reverted", "wikieditor"], "is_revert": false, "reverted_editor": null}, {"revid": 1355691333, "parentid": 1355691274, "user": "R.tuor", "timestamp": "2026-05-23T09:34:05Z", "size": 221406, "sha1": "c5f995f5dc9795c4ef0d128259343343580a4edb", "comment": "", "tags": ["mw-reverted", "wikieditor"], "is_revert": false, "reverted_editor": null}, {"revid": 1355728293, "parentid": 1355691333, "user": "Kodak11111", "timestamp": "2026-05-23T15:32:37Z", "size": 220740, "sha1": "0ed0c619a2de21e5f8c49fb4c1863982319790dc", "comment": "Undid 3 revisions from [[Special:Diff/1355690957|1355690957]] until [[Special:Diff/1355691333|1355691333]] undo weight for intro, covered in Controversies section", "tags": ["mw-undo", "wikieditor"], "is_revert": true, "reverted_editor": "R.tuor"}, {"revid": 1355753941, "parentid": 1355728293, "user": "MajorLeagueSoccerFan", "timestamp": "2026-05-23T18:53:41Z", "size": 220571, "sha1": "87f5f88707ece50fa6b4a817398be34a08613a43", "comment": "/* Team base camps */", "tags": ["wikieditor"], "is_revert": false, "reverted_editor": null}, {"revid": 1355853728, "parentid": 1355753941, "user": "Emperorpenguinn", "timestamp": "2026-05-24T08:03:24Z", "size": 221187, "sha1": "04826e2bc7adeb2696a50cde630c40f704cc7198", "comment": "/* Controversies */ Added Ebola quarantine subsection", "tags": ["visualeditor-wikitext"], "is_revert": false, "reverted_editor": null}, {"revid": 1355873853, "parentid": 1355853728, "user": "Cyfraw", "timestamp": "2026-05-24T11:48:47Z", "size": 221200, "sha1": "354750bd50f76320bd57ceea979337fa288e39dd", "comment": "/* Immigration */", "tags": ["visualeditor-wikitext"], "is_revert": false, "reverted_editor": null}, {"revid": 1355886885, "parentid": 1355873853, "user": "Assadzadeh", "timestamp": "2026-05-24T13:52:15Z", "size": 221196, "sha1": "00dc52cb4b76e55ae59ff4e3fb18c75a6997d930", "comment": "/* Immigration */ Copyedit (minor)", "tags": ["wikieditor"], "is_revert": false, "reverted_editor": null}, {"revid": 1355887486, "parentid": 1355886885, "user": "Assadzadeh", "timestamp": "2026-05-24T13:57:43Z", "size": 221222, "sha1": "302d58278c24fec9b2b3f79d8a71d21c29da8ed4", "comment": "/* Ebola quarantine */ Fixed reference", "tags": ["wikieditor"], "is_revert": false, "reverted_editor": null}, {"revid": 1355899088, "parentid": 1355887486, "user": "DannyCutterAnderson", "timestamp": "2026-05-24T15:32:00Z", "size": 221224, "sha1": "a96802303293a699c9d5f2d452a31579e72b4bd9", "comment": "/* */ America you really are not the center of the world.", "tags": ["mobile edit", "mobile web edit", "mw-reverted"], "is_revert": false, "reverted_editor": null}, {"revid": 1355899302, "parentid": 1355899088, "user": "1995hoo", "timestamp": "2026-05-24T15:33:50Z", "size": 221222, "sha1": "302d58278c24fec9b2b3f79d8a71d21c29da8ed4", "comment": "Undid revision [[Special:Diff/1355899088|1355899088]] by [[Special:Contributions/DannyCutterAnderson|DannyCutterAnderson]] ([[User talk:DannyCutterAnderson|talk]])\u2014obvious bad faith, given the edit summary.", "tags": ["mw-undo", "wikieditor"], "is_revert": true, "reverted_editor": "DannyCutterAnderson"}, {"revid": 1355943552, "parentid": 1355899302, "user": "Sangeth30", "timestamp": "2026-05-24T21:05:42Z", "size": 221320, "sha1": "2fa125905f64b7c8daa1a8a7c1a34a161cd06d04", "comment": "", "tags": ["visualeditor", "mw-reverted"], "is_revert": false, "reverted_editor": null}, {"revid": 1355944316, "parentid": 1355943552, "user": "Sangeth30", "timestamp": "2026-05-24T21:09:35Z", "size": 221454, "sha1": "c71abef3cc3e10529874d5fecaf79c110fba7f55", "comment": "", "tags": ["visualeditor", "mw-reverted"], "is_revert": false, "reverted_editor": null}, {"revid": 1355944546, "parentid": 1355944316, "user": "Sangeth30", "timestamp": "2026-05-24T21:11:03Z", "size": 221498, "sha1": "cd77fc47599841e31e43e6c449e2d49ff1c0dce8", "comment": "", "tags": ["visualeditor", "mw-reverted"], "is_revert": false, "reverted_editor": null}, {"revid": 1355947305, "parentid": 1355944546, "user": "Kodak11111", "timestamp": "2026-05-24T21:27:33Z", "size": 221222, "sha1": "302d58278c24fec9b2b3f79d8a71d21c29da8ed4", "comment": "Undid 3 revisions from [[Special:Diff/1355943552|1355943552]] until [[Special:Diff/1355944546|1355944546]] redundant info already mentioned", "tags": ["mw-undo", "wikieditor"], "is_revert": true, "reverted_editor": "Sangeth30"}, {"revid": 1355965885, "parentid": 1355947305, "user": "DannyCutterAnderson", "timestamp": "2026-05-24T23:59:43Z", "size": 221226, "sha1": "1a8649b18bc6e4c2703c048f57637d63cce06f66", "comment": "", "tags": ["mw-reverted", "wikieditor"], "is_revert": false, "reverted_editor": null}, {"revid": 1355966023, "parentid": 1355965885, "user": "Kodak11111", "timestamp": "2026-05-25T00:00:43Z", "size": 221222, "sha1": "302d58278c24fec9b2b3f79d8a71d21c29da8ed4", "comment": "Undid revision [[Special:Diff/1355965885|1355965885]] by [[Special:Contributions/DannyCutterAnderson|DannyCutterAnderson]] ([[User talk:DannyCutterAnderson|talk]]) read the comment", "tags": ["mw-undo", "mobile edit", "mobile web edit", "advanced mobile edit", "wikieditor"], "is_revert": true, "reverted_editor": "DannyCutterAnderson"}, {"revid": 1355999497, "parentid": 1355966023, "user": "DividedFrame", "timestamp": "2026-05-25T04:32:40Z", "size": 221692, "sha1": "fc99d876331e9b4ae5114eb716d2f7028f0fc210", "comment": "/* FIFA fan festivals */ Atlanta", "tags": ["wikieditor"], "is_revert": false, "reverted_editor": null}, {"revid": 1356023956, "parentid": 1355999497, "user": "R.tuor", "timestamp": "2026-05-25T08:51:59Z", "size": 222135, "sha1": "9d3ab15b1920a382f479d6f76f4542e5e8b2dfbb", "comment": "/* Iran's participation */", "tags": ["wikieditor"], "is_revert": false, "reverted_editor": null}, {"revid": 1356065062, "parentid": 1356023956, "user": "HalfOfAnOrange", "timestamp": "2026-05-25T14:47:22Z", "size": 222299, "sha1": "e07e61176318663f020730e802ce9f655bf7d104", "comment": "/* Domestic sponsors */", "tags": ["wikieditor"], "is_revert": false, "reverted_editor": null}, {"revid": 1356065987, "parentid": 1356065062, "user": "HalfOfAnOrange", "timestamp": "2026-05-25T14:54:29Z", "size": 222346, "sha1": "ee5f2d999c7b5cf929b174e14ee396b862cf4d5d", "comment": "/* Domestic sponsors */", "tags": ["wikieditor"], "is_revert": false, "reverted_editor": null}, {"revid": 1356067026, "parentid": 1356065987, "user": "HalfOfAnOrange", "timestamp": "2026-05-25T15:02:34Z", "size": 223152, "sha1": "d6a5c881124f6225174c20f09ffc31394faabd09", "comment": "/* Domestic sponsors */", "tags": ["wikieditor"], "is_revert": false, "reverted_editor": null}, {"revid": 1356067082, "parentid": 1356067026, "user": "HalfOfAnOrange", "timestamp": "2026-05-25T15:03:03Z", "size": 223158, "sha1": "309fc6260d38b833272ca522b46694e9f17bd566", "comment": "/* Domestic sponsors */", "tags": ["wikieditor"], "is_revert": false, "reverted_editor": null}, {"revid": 1356070036, "parentid": 1356067082, "user": "Assadzadeh", "timestamp": "2026-05-25T15:26:36Z", "size": 223215, "sha1": "a383ec2b150cd8292145450ba625bef39fbb5437", "comment": "/* Iran's participation */ Added missing author", "tags": ["wikieditor"], "is_revert": false, "reverted_editor": null}, {"revid": 1356110635, "parentid": 1356070036, "user": "HalfOfAnOrange", "timestamp": "2026-05-25T20:31:17Z", "size": 223249, "sha1": "5f237bd9132ce7d2977a84f19f4d8e2acab99bf7", "comment": "/* Team base camps */", "tags": ["wikieditor"], "is_revert": false, "reverted_editor": null}, {"revid": 1356110811, "parentid": 1356110635, "user": "HalfOfAnOrange", "timestamp": "2026-05-25T20:32:29Z", "size": 223279, "sha1": "294a9f65c71605a2f3563191eab9166846fe7af0", "comment": "/* Team base camps */", "tags": ["wikieditor"], "is_revert": false, "reverted_editor": null}, {"revid": 1356111616, "parentid": 1356110811, "user": "HalfOfAnOrange", "timestamp": "2026-05-25T20:38:05Z", "size": 220573, "sha1": "5ebf108e1d554cbc45b85c5d6e8625f0f8fbe870", "comment": "/* Team base camps */  fifa has confirmed today https://inside.fifa.com/organisation/media-releases/world-cup-2026-team-base-camps-tbc-48-nations-usa-mexico-canada", "tags": ["wikieditor"], "is_revert": false, "reverted_editor": null}, {"revid": 1356122967, "parentid": 1356111616, "user": "Oliklixer", "timestamp": "2026-05-25T21:47:06Z", "size": 220585, "sha1": "a5c24f296402f1506bae56ba9ab83b6501a0798e", "comment": "", "tags": ["visualeditor", "mw-reverted"], "is_revert": false, "reverted_editor": null}, {"revid": 1356138030, "parentid": 1356122967, "user": "Kodak11111", "timestamp": "2026-05-25T23:25:44Z", "size": 220573, "sha1": "5ebf108e1d554cbc45b85c5d6e8625f0f8fbe870", "comment": "Undid revision [[Special:Diff/1356122967|1356122967]] by [[Special:Contributions/Oliklixer|Oliklixer]] ([[User talk:Oliklixer|talk]]) [[WP:OVERLINK]]", "tags": ["mw-undo", "mobile edit", "mobile web edit", "advanced mobile edit", "wikieditor"], "is_revert": true, "reverted_editor": "Oliklixer"}, {"revid": 1356144016, "parentid": 1356138030, "user": "Patmaher", "timestamp": "2026-05-26T00:15:35Z", "size": 220572, "sha1": "a9fb6931b8c83b887ffa417331fe8beec1e0eb03", "comment": "/* Team base camps */", "tags": ["wikieditor"], "is_revert": false, "reverted_editor": null}, {"revid": 1356175264, "parentid": 1356144016, "user": "Furlanija", "timestamp": "2026-05-26T03:50:17Z", "size": 220611, "sha1": "cfb6cdaf9f20d490e64e6e777623c28d26660cef", "comment": "/* Ebola quarantine */ Linked the Ebola outbreak", "tags": ["mobile edit", "mobile web edit"], "is_revert": false, "reverted_editor": null}, {"revid": 1356213520, "parentid": 1356175264, "user": "Tobby72", "timestamp": "2026-05-26T10:57:27Z", "size": 222050, "sha1": "eba36932b1fdb16cedb1c391ddd42d13b750d613", "comment": "relevant, cited", "tags": ["mw-reverted", "wikieditor"], "is_revert": false, "reverted_editor": null}, {"revid": 1356217223, "parentid": 1356213520, "user": "1995hoo", "timestamp": "2026-05-26T11:35:03Z", "size": 222055, "sha1": "a95461d12d7c230ee224876f04793643be02dce6", "comment": "/* Discussions of a possible boycott over Greenland */ wording.", "tags": ["mw-reverted", "wikieditor"], "is_revert": false, "reverted_editor": null}, {"revid": 1356231111, "parentid": 1356217223, "user": "Kodak11111", "timestamp": "2026-05-26T13:54:29Z", "size": 222058, "sha1": "ba7c141a1488b14043c57c0490a1e5fd9d80d261", "comment": "/* Discussions of a possible boycott over Greenland */", "tags": ["mobile edit", "mobile web edit", "advanced mobile edit", "mw-reverted"], "is_revert": false, "reverted_editor": null}, {"revid": 1356232422, "parentid": 1356231111, "user": "Chris1834", "timestamp": "2026-05-26T14:07:44Z", "size": 220611, "sha1": "cfb6cdaf9f20d490e64e6e777623c28d26660cef", "comment": "Restored revision 1356175264 by [[Special:Contributions/Furlanija|Furlanija]] ([[User talk:Furlanija|talk]]): This still exits, it was just moved to the list article.", "tags": ["mw-undo", "twinkle"], "is_revert": true, "reverted_editor": "Kodak11111"}, {"revid": 1356246415, "parentid": 1356232422, "user": "Sangeth30", "timestamp": "2026-05-26T16:08:58Z", "size": 221483, "sha1": "c9e2607e71868e29a8f2fdc2ab6dc0a638262533", "comment": "/* Awards */  Added individual awards section", "tags": ["visualeditor", "editcheck-references", "editcheck-newcontent", "editcheck-references-shown"], "is_revert": false, "reverted_editor": null}, {"revid": 1356246916, "parentid": 1356246415, "user": "Sangeth30", "timestamp": "2026-05-26T16:12:37Z", "size": 222532, "sha1": "7c9c9a8e70d54dd1488f0cff6be74f22a8f2c1be", "comment": "", "tags": ["visualeditor", "deprecated source", "mw-reverted", "editcheck-newreference", "editsuggestion-seen", "editsuggestion-used"], "is_revert": false, "reverted_editor": null}, {"revid": 1356248598, "parentid": 1356246916, "user": "McSly", "timestamp": "2026-05-26T16:27:11Z", "size": 221483, "sha1": "c9e2607e71868e29a8f2fdc2ab6dc0a638262533", "comment": "Undid revision [[Special:Diff/1356246916|1356246916]] by [[Special:Contributions/Sangeth30|Sangeth30]] ([[User talk:Sangeth30|talk]]) You can't use WP as a source. See [[WP:CIRCULAR]]", "tags": ["mw-undo", "wikieditor"], "is_revert": true, "reverted_editor": "Sangeth30"}, {"revid": 1356249163, "parentid": 1356248598, "user": "Kodak11111", "timestamp": "2026-05-26T16:30:51Z", "size": 221154, "sha1": "0bd1bac2643919a467a1da3406151950ec160116", "comment": "/* Individual and team awards */", "tags": ["mobile edit", "mobile web edit", "advanced mobile edit"], "is_revert": false, "reverted_editor": null}, {"revid": 1356263486, "parentid": 1356249163, "user": "Chris1834", "timestamp": "2026-05-26T18:25:14Z", "size": 221155, "sha1": "f17dcb0cd1c1653e272d02c71ed90667c51816a8", "comment": "/* Individual and team awards */ wording", "tags": ["visualeditor-wikitext"], "is_revert": false, "reverted_editor": null}, {"revid": 1356338199, "parentid": 1356263486, "user": "Ronnnaldo7", "timestamp": "2026-05-27T04:25:21Z", "size": 221530, "sha1": "0a569c6264a5e18936bad43176e2473530c5637c", "comment": "Update", "tags": ["wikieditor"], "is_revert": false, "reverted_editor": null}, {"revid": 1356347207, "parentid": 1356338199, "user": "HalfOfAnOrange", "timestamp": "2026-05-27T05:32:19Z", "size": 221957, "sha1": "5664cb0c199c85410d16b3949cbf5714d19d571e", "comment": "/* Iran's participation */", "tags": ["wikieditor"], "is_revert": false, "reverted_editor": null}, {"revid": 1356380074, "parentid": 1356347207, "user": "1995hoo", "timestamp": "2026-05-27T12:03:27Z", "size": 221958, "sha1": "789267372f54f976cceba15039e9102096b775dd", "comment": "/* Iran's participation */ grammar and capitalization.", "tags": ["wikieditor"], "is_revert": false, "reverted_editor": null}, {"revid": 1356384586, "parentid": 1356380074, "user": "Cyfraw", "timestamp": "2026-05-27T12:46:04Z", "size": 222241, "sha1": "c73a8274245ce1fbf9663cae2b9d1477ff9af74f", "comment": "/* Team base camps */ +Update referenece", "tags": ["visualeditor-wikitext"], "is_revert": false, "reverted_editor": null}, {"revid": 1356387616, "parentid": 1356384586, "user": "Kodak11111", "timestamp": "2026-05-27T13:11:54Z", "size": 222243, "sha1": "9666f070a9b829b643ccc474d2ba7a45859d9247", "comment": "/* Team base camps */ MDY", "tags": ["mobile edit", "mobile web edit", "advanced mobile edit"], "is_revert": false, "reverted_editor": null}, {"revid": 1356387862, "parentid": 1356387616, "user": "Kodak11111", "timestamp": "2026-05-27T13:14:20Z", "size": 222616, "sha1": "cab51e37db8af0cdd988754306caba6d02579a4d", "comment": "/* Video games */ reference format", "tags": ["mobile edit", "mobile web edit", "visualeditor", "advanced mobile edit"], "is_revert": false, "reverted_editor": null}, {"revid": 1356403308, "parentid": 1356387862, "user": "Assadzadeh", "timestamp": "2026-05-27T15:16:31Z", "size": 222641, "sha1": "8ca578c2621316774fb9b4f590cbadd2e2e435e6", "comment": "/* Iran's participation */ Added retrieved date", "tags": ["wikieditor"], "is_revert": false, "reverted_editor": null}, {"revid": 1356420830, "parentid": 1356403308, "user": "HalfOfAnOrange", "timestamp": "2026-05-27T17:23:05Z", "size": 222624, "sha1": "e83255e80ec1e361f7ec2effdbcb8f1ef7a38c8a", "comment": "/* Iran's participation */", "tags": ["wikieditor"], "is_revert": false, "reverted_editor": null}, {"revid": 1356420868, "parentid": 1356420830, "user": "HalfOfAnOrange", "timestamp": "2026-05-27T17:23:18Z", "size": 222624, "sha1": "ecf7d10318eafeb9f1ebfedf98125935829987a7", "comment": "/* Iran's participation */", "tags": ["wikieditor"], "is_revert": false, "reverted_editor": null}, {"revid": 1356456231, "parentid": 1356420868, "user": "Roaring phoenix", "timestamp": "2026-05-27T21:37:42Z", "size": 222620, "sha1": "1a487c61a757f1e5d4be1bd2f56a0db9bc3fab68", "comment": "I have replaced 'Cup \u2014 Algeria,' with 'Cup\u2014Algeria,' and 'Tunisia \u2014 as' with ''Tunisia\u2014as'.", "tags": ["wikieditor"], "is_revert": false, "reverted_editor": null}, {"revid": 1356458938, "parentid": 1356456231, "user": "EncyClaresh1810", "timestamp": "2026-05-27T22:01:35Z", "size": 222628, "sha1": "c2482586c505816f5b202005af18776035ddeb29", "comment": "", "tags": ["mobile edit", "mobile web edit", "visualeditor"], "is_revert": false, "reverted_editor": null}, {"revid": 1356481534, "parentid": 1356458938, "user": "Bennett Li11", "timestamp": "2026-05-28T01:26:21Z", "size": 222653, "sha1": "d62ea2cda769dd86d3ee3312907b679fe4294d64", "comment": "Linked", "tags": ["visualeditor"], "is_revert": false, "reverted_editor": null}, {"revid": 1356485938, "parentid": 1356481534, "user": "Another Believer", "timestamp": "2026-05-28T02:01:54Z", "size": 222667, "sha1": "43f5e0a4b00b992ba6fbd40ab6b00c4632342b92", "comment": "+", "tags": ["wikieditor"], "is_revert": false, "reverted_editor": null}, {"revid": 1356489080, "parentid": 1356485938, "user": "AnomieBOT", "timestamp": "2026-05-28T02:22:50Z", "size": 222681, "sha1": "2e1a6e1138f134a10364dace23e13a977ebc01d2", "comment": "Dating maintenance tags: {{Bare URLs}}", "tags": [], "is_revert": false, "reverted_editor": null}, {"revid": 1356504668, "parentid": 1356489080, "user": "Kodak11111", "timestamp": "2026-05-28T04:34:55Z", "size": 223404, "sha1": "83fdcf63c61a383bd017ca0be3dc31f76ba2e4da", "comment": "/* Opening ceremonies */ references", "tags": ["mobile edit", "mobile web edit", "visualeditor", "advanced mobile edit", "editcheck-newreference"], "is_revert": false, "reverted_editor": null}, {"revid": 1356505030, "parentid": 1356504668, "user": "Kodak11111", "timestamp": "2026-05-28T04:38:35Z", "size": 223693, "sha1": "a147e422f5a1fd60dc9c6331d27df3a6136498f3", "comment": "", "tags": ["mobile edit", "mobile web edit", "advanced mobile edit"], "is_revert": false, "reverted_editor": null}, {"revid": 1356505958, "parentid": 1356505030, "user": "Kodak11111", "timestamp": "2026-05-28T04:45:07Z", "size": 224127, "sha1": "d57f551a154371e03fa5fb1079655b7fe270b3a4", "comment": "/* Iran's participation */", "tags": ["mobile edit", "mobile web edit", "visualeditor", "advanced mobile edit"], "is_revert": false, "reverted_editor": null}, {"revid": 1356506066, "parentid": 1356505958, "user": "Kodak11111", "timestamp": "2026-05-28T04:46:02Z", "size": 224097, "sha1": "531aff1bc731104a231db920664eb807a92175b2", "comment": "/* */", "tags": ["mobile edit", "mobile web edit", "advanced mobile edit"], "is_revert": false, "reverted_editor": null}, {"revid": 1356617949, "parentid": 1356506066, "user": "Fylindfotberserk", "timestamp": "2026-05-28T21:16:17Z", "size": 224106, "sha1": "b3601681f86ea69568501cf0e3e2e7153ac2d7b3", "comment": "[[Wikipedia:MOSNUMscript|script]]-assisted date audit and style fixes per [[MOS:NUM]]", "tags": ["wikieditor"], "is_revert": false, "reverted_editor": null}, {"revid": 1356648654, "parentid": 1356617949, "user": "Meganinja202", "timestamp": "2026-05-29T00:59:41Z", "size": 224162, "sha1": "163f376bec41793aab8b22a08a3061ca5bcbe8f5", "comment": "/* Video games */ - world cup licenced game lincensed", "tags": ["visualeditor", "editcheck-newreference", "editcheck-newcontent"], "is_revert": false, "reverted_editor": null}, {"revid": 1356657347, "parentid": 1356648654, "user": "Kodak11111", "timestamp": "2026-05-29T02:05:25Z", "size": 223840, "sha1": "3a54513044ef55bea86462fa66b0297a07b2bb0d", "comment": "/* Video games */", "tags": ["mobile edit", "mobile web edit", "visualeditor", "advanced mobile edit", "editcheck-newreference"], "is_revert": false, "reverted_editor": null}, {"revid": 1356686492, "parentid": 1356657347, "user": "Ronnnaldo7", "timestamp": "2026-05-29T05:58:52Z", "size": 224960, "sha1": "9d65929c808a7a93da90583c46188dde2bd9f26c", "comment": "Update", "tags": ["wikieditor"], "is_revert": false, "reverted_editor": null}, {"revid": 1356688121, "parentid": 1356686492, "user": "Ronnnaldo7", "timestamp": "2026-05-29T06:14:45Z", "size": 224984, "sha1": "5586b65ac6e06cdbf9ebfda50dd666cada87ad79", "comment": "Update per source", "tags": ["wikieditor"], "is_revert": false, "reverted_editor": null}, {"revid": 1356692119, "parentid": 1356688121, "user": "Meganinja202", "timestamp": "2026-05-29T06:52:58Z", "size": 224782, "sha1": "b950c2078a7964933a5f992ebabec32306bd0d17", "comment": "/* Video games */ - focus in the segment should be on the licncend games, if EA FC doesnt have tournament licence then it should not be featured", "tags": ["visualeditor", "editcheck-newreference", "editcheck-newcontent"], "is_revert": false, "reverted_editor": null}, {"revid": 1356692224, "parentid": 1356692119, "user": "Meganinja202", "timestamp": "2026-05-29T06:53:56Z", "size": 224782, "sha1": "06d77567f66ab6a9af6c66364320f752f7aa7424", "comment": "/* Video games */", "tags": ["visualeditor"], "is_revert": false, "reverted_editor": null}, {"revid": 1356692638, "parentid": 1356692224, "user": "Meganinja202", "timestamp": "2026-05-29T06:58:16Z", "size": 224781, "sha1": "3121c4b21e044c2935cb3a596872f1b1bc964b8c", "comment": "- typo", "tags": ["visualeditor"], "is_revert": false, "reverted_editor": null}, {"revid": 1356726510, "parentid": 1356692638, "user": "OblongBubbles", "timestamp": "2026-05-29T13:19:36Z", "size": 224663, "sha1": "99df4a05c8798e20259f5887c5551a36d6ed1408", "comment": "/* Video games */ typos, clearing up wording.", "tags": ["wikieditor"], "is_revert": false, "reverted_editor": null}, {"revid": 1356727478, "parentid": 1356726510, "user": "Chris1834", "timestamp": "2026-05-29T13:28:20Z", "size": 224641, "sha1": "87c6580d83cf66449cdcffdc54b13398125d3759", "comment": "/* Video games */ c/e", "tags": ["visualeditor-switched", "wikieditor"], "is_revert": false, "reverted_editor": null}, {"revid": 1356727562, "parentid": 1356727478, "user": "Chris1834", "timestamp": "2026-05-29T13:29:11Z", "size": 224637, "sha1": "eccb6337616613d7e5e47fd5a7207f06725b65fa", "comment": "/* Video games */ c/e", "tags": ["visualeditor-wikitext"], "is_revert": false, "reverted_editor": null}, {"revid": 1356729653, "parentid": 1356727562, "user": "Fylindfotberserk", "timestamp": "2026-05-29T13:47:57Z", "size": 224641, "sha1": "6234ba440c6e8213869d1f67d29c74bb91a0fcde", "comment": "[[Wikipedia:MOSNUMscript|script]]-assisted date audit and style fixes per [[MOS:NUM]]", "tags": ["wikieditor"], "is_revert": false, "reverted_editor": null}, {"revid": 1356731488, "parentid": 1356729653, "user": "HalfOfAnOrange", "timestamp": "2026-05-29T14:05:39Z", "size": 225280, "sha1": "dd49fa4780b03d391f8fd1f0da8977f6061eb752", "comment": "/* Opening ceremonies */", "tags": ["wikieditor"], "is_revert": false, "reverted_editor": null}, {"revid": 1356736322, "parentid": 1356731488, "user": "HalfOfAnOrange", "timestamp": "2026-05-29T14:43:58Z", "size": 225509, "sha1": "cfda63d64fc42c15978af2a85205e8fdaf809765", "comment": "/* Domestic sponsors */", "tags": ["wikieditor"], "is_revert": false, "reverted_editor": null}, {"revid": 1356769885, "parentid": 1356736322, "user": "CUA 27", "timestamp": "2026-05-29T18:34:43Z", "size": 225505, "sha1": "5a4f2e9179b48c3bfa7871c7332fd30a1fd6b7a1", "comment": "/* Squads */", "tags": ["wikieditor"], "is_revert": false, "reverted_editor": null}, {"revid": 1356785976, "parentid": 1356769885, "user": "HalfOfAnOrange", "timestamp": "2026-05-29T20:21:41Z", "size": 226032, "sha1": "634df8f99f4c2b2a47a8446918bd7924f6f934b0", "comment": "/* Music */", "tags": ["wikieditor"], "is_revert": false, "reverted_editor": null}, {"revid": 1356793432, "parentid": 1356785976, "user": "Kodak11111", "timestamp": "2026-05-29T21:15:10Z", "size": 226033, "sha1": "893aa7bf838af58bcc6473a39c7536a9a39aa647", "comment": "/* Music */ This paragraph should be reformatted into a table", "tags": ["mobile edit", "mobile web edit", "advanced mobile edit"], "is_revert": false, "reverted_editor": null}, {"revid": 1356794741, "parentid": 1356793432, "user": "Kodak11111", "timestamp": "2026-05-29T21:25:33Z", "size": 222838, "sha1": "8bc8805b4c05bd4fe66612b92a5330dd5ef82ad6", "comment": "Made into table. Listing of remix artists not needed, can see the main page for that", "tags": ["mobile edit", "mobile web edit", "advanced mobile edit"], "is_revert": false, "reverted_editor": null}, {"revid": 1356856330, "parentid": 1356794741, "user": "R.tuor", "timestamp": "2026-05-30T06:51:06Z", "size": 223229, "sha1": "541af31b0f356225381081867d1f057f6755c6f7", "comment": "/* Iran's participation */", "tags": ["mw-reverted", "wikieditor"], "is_revert": false, "reverted_editor": null}, {"revid": 1356857387, "parentid": 1356856330, "user": "Kodak11111", "timestamp": "2026-05-30T07:03:35Z", "size": 222838, "sha1": "8bc8805b4c05bd4fe66612b92a5330dd5ef82ad6", "comment": "Undid revision [[Special:Diff/1356856330|1356856330]] by [[Special:Contributions/R.tuor|R.tuor]] ([[User talk:R.tuor|talk]]) Although true, I don't think this meets the materiality threshold to be included", "tags": ["mw-undo", "mobile edit", "mobile web edit", "advanced mobile edit", "wikieditor"], "is_revert": true, "reverted_editor": "R.tuor"}, {"revid": 1356857545, "parentid": 1356857387, "user": "Kodak11111", "timestamp": "2026-05-30T07:05:31Z", "size": 222842, "sha1": "d8afa3689f05467fa9b0326e952c65e18882d4cd", "comment": "/* Iran's participation */", "tags": ["mobile edit", "mobile web edit", "advanced mobile edit"], "is_revert": false, "reverted_editor": null}, {"revid": 1356860884, "parentid": 1356857545, "user": "VonXionixx87", "timestamp": "2026-05-30T07:50:30Z", "size": 222846, "sha1": "87f68df25cadb1611fb989e00023e23dad54c165", "comment": "/* Music */", "tags": ["wikieditor"], "is_revert": false, "reverted_editor": null}, {"revid": 1356901877, "parentid": 1356860884, "user": "HalfOfAnOrange", "timestamp": "2026-05-30T14:53:54Z", "size": 222980, "sha1": "2bd91ab0d78394e98dd46c81f107e46b6934ef6d", "comment": "/* Domestic sponsors */", "tags": ["wikieditor"], "is_revert": false, "reverted_editor": null}, {"revid": 1356902769, "parentid": 1356901877, "user": "HalfOfAnOrange", "timestamp": "2026-05-30T14:59:55Z", "size": 223040, "sha1": "0196803a0fa0af916a6de236e899cc475c37a8ac", "comment": "/* Domestic sponsors */", "tags": ["wikieditor"], "is_revert": false, "reverted_editor": null}, {"revid": 1357012451, "parentid": 1356902769, "user": "Renerpho", "timestamp": "2026-05-31T06:49:20Z", "size": 224046, "sha1": "02f8577dad67d12c828b8b6922e653616e813e87", "comment": "/* Ebola quarantine */ Colombia response", "tags": ["wikieditor"], "is_revert": false, "reverted_editor": null}, {"revid": 1357012507, "parentid": 1357012451, "user": "Renerpho", "timestamp": "2026-05-31T06:49:53Z", "size": 224052, "sha1": "390461f4d43eca97219d20e548446da9917fab78", "comment": "/* Ebola quarantine */ date format", "tags": ["wikieditor"], "is_revert": false, "reverted_editor": null}, {"revid": 1357012576, "parentid": 1357012507, "user": "Renerpho", "timestamp": "2026-05-31T06:50:38Z", "size": 224053, "sha1": "88396a515369ca4e28d459cb9cc78c9006087bb4", "comment": "/* Ebola quarantine */ definite article", "tags": ["wikieditor"], "is_revert": false, "reverted_editor": null}, {"revid": 1357076227, "parentid": 1357012576, "user": "Rushtheeditor", "timestamp": "2026-05-31T16:43:45Z", "size": 224350, "sha1": "f9175da4e233c875d05995cb0813e622705322c2", "comment": "/* FIFA fan festivals */", "tags": ["wikieditor"], "is_revert": false, "reverted_editor": null}, {"revid": 1357109485, "parentid": 1357076227, "user": "Jkudlick", "timestamp": "2026-05-31T20:20:41Z", "size": 224350, "sha1": "319dcf2979f535ee67084d3df46c0c4d8dcc2118", "comment": "/* Tickets */ correction per talk page request", "tags": ["wikieditor"], "is_revert": false, "reverted_editor": null}, {"revid": 1357116999, "parentid": 1357109485, "user": "Joalbertine", "timestamp": "2026-05-31T21:09:49Z", "size": 224352, "sha1": "ca6592c644448dba2f28b07c201fbf314d940d74", "comment": "Updated short description", "tags": ["mobile edit", "mobile app edit", "android app edit", "advanced mobile edit", "mw-reverted", "app-description-change"], "is_revert": false, "reverted_editor": null}, {"revid": 1357123313, "parentid": 1357116999, "user": "Kodak11111", "timestamp": "2026-05-31T21:49:36Z", "size": 224753, "sha1": "dd60566ccc36495e1c68128fe31d9f22c4f2ed31", "comment": "/* FIFA fan festivals */", "tags": ["mobile edit", "mobile web edit", "visualeditor", "advanced mobile edit"], "is_revert": false, "reverted_editor": null}, {"revid": 1357131065, "parentid": 1357123313, "user": "Jkudlick", "timestamp": "2026-05-31T22:44:52Z", "size": 224751, "sha1": "1560e28fd3078f588fd4604b4ce695a955f98ad8", "comment": "Undid revision [[Special:Diff/1357116999|1357116999]] by [[Special:Contributions/Joalbertine|Joalbertine]] ([[User talk:Joalbertine|talk]]) [[MOS:ENGVAR]] {{Use American English}}", "tags": ["mw-undo", "wikieditor"], "is_revert": true, "reverted_editor": "Kodak11111"}]